Workbook

Sheet P&L
B1: =INPUTS!C5 -> New Conference 2027
B2: =INPUTS!C6&" | "&INPUTS!C7&" | "&TEXT(INPUTS!C18,"0")&" event days + "&TEXT(INPUTS!C19,"0")&" set-up | "&TEXT(INPUTS!C22,"0")&" months planning" -> April 6-8, 2027 | Los Angeles, CA | 3 event days + 1 set-up | 9 months planning
B4: PROPOSAL SUMMARY
B5: ITEM | C5: CLIENT COST | D5: OUR COST | E5: NET PROFIT | F5: % Profit
B6: ="Project Hours ("&TEXT(D43,"#,##0")&")" -> Project Hours (568) | C6: =E43 -> 48830 | D6: =H43 -> 32244 | E6: =C6-D6 -> 16586 | F6: =IF(C6=0,"",E6/C6) -> 0.33966824
B7: ="Onsite Management ("&TEXT(D68,"#,##0")&")" -> Onsite Management (224) | C7: =E68 -> 20120 | D7: =H68 -> 12336 | E7: =C7-D7 -> 7784 | F7: =IF(C7=0,"",E7/C7) -> 0.38687873
B8: ="Staff Overhead ("&TEXT(INPUTS!$C$48,"$0.00")&" / staff hour)" -> Staff Overhead ($0.61 / staff hour) | C8: 0 | D8: =E74 -> 483.12 | E8: =C8-D8 -> -483.12 | F8: =IF(C8=0,"",E8/C8)
B9: TOTALS | C9: =SUM(C6:C8) -> 68950 | D9: =SUM(D6:D8) -> 45063.12 | E9: =SUM(E6:E8) -> 23886.88 | F9: =IF(C9=0,"",E9/C9) -> 0.34643771
B10: ="Admin Fee ("&TEXT(INPUTS!$C$49,"0.0%")&")" -> Admin Fee (2.0%) | C10: =C9*INPUTS!$C$49 -> 1379 | D10: 0 | E10: =C10-D10 -> 1379
B11: ="Less Multi-Year Discount ("&TEXT(INPUTS!$C$50,"0.0%")&")" -> Less Multi-Year Discount (5.0%) | C11: =-IF(INPUTS!$C$51="Yes",(C9+C10)*INPUTS!$C$50,0) -> 0 | D11: 0 | E11: =C11-D11 -> 0
B12: GRAND TOTAL | C12: =SUM(C9:C11) -> 70329 | D12: =SUM(D9:D11) -> 45063.12 | E12: =SUM(E9:E11) -> 25265.88 | F12: =IF(C12=0,"",E12/C12) -> 0.35925266
B14: PRE-PLANNING HOURS BY STAFF CATEGORY
B15: CATEGORY | C15: HOURS | D15: OUR RATE / HR | E15: OUR COST | F15: STAFF COUNT | G15: HRS / PERSON / WEEK
B16: Managers | C16: =SUMIFS(SCOPE!$I$4:$I$59,SCOPE!$D$4:$D$59,"Manager",SCOPE!$E$4:$E$59,"Yes") -> 336 | D16: =INPUTS!$C$33 -> 60 | E16: =C16*D16 -> 20160 | F16: =INPUTS!$C$29 -> 1 | G16: =IF(OR(F16=0,INPUTS!$C$23=0),"",C16/F16/INPUTS!$C$23) -> 8.6153846
B17: Coordinators | C17: =SUMIFS(SCOPE!$I$4:$I$59,SCOPE!$D$4:$D$59,"Coordinator",SCOPE!$E$4:$E$59,"Yes") -> 193 | D17: =INPUTS!$C$34 -> 42 | E17: =C17*D17 -> 8106 | F17: =INPUTS!$C$30 -> 1 | G17: =IF(OR(F17=0,INPUTS!$C$23=0),"",C17/F17/INPUTS!$C$23) -> 4.9487179
B18: Team (weekly meetings) | C18: =SUMIFS(SCOPE!$I$4:$I$59,SCOPE!$D$4:$D$59,"Team",SCOPE!$E$4:$E$59,"Yes") -> 39 | D18: =INPUTS!$C$29*INPUTS!$C$33+INPUTS!$C$30*INPUTS!$C$34 -> 102 | E18: =C18*D18 -> 3978 | F18: =INPUTS!$C$29+INPUTS!$C$30 -> 2 | G18: =IF(INPUTS!$C$23=0,"",C18/INPUTS!$C$23) -> 1
B19: TOTAL PRE-PLANNING | C19: =SUM(C16:C18) -> 568 | E19: =SUM(E16:E18) -> 32244 | F19: =INPUTS!$C$29+INPUTS!$C$30 -> 2
B20: HRS / PERSON / WEEK is the workload check — above roughly 10, add staff or trim scope.
B21: EVENT MANAGEMENT
B22: SCOPE OF WORK | C22: CLIENT RATE | D22: HOURS | E22: CLIENT COST | F22: OUR RATE | G22: HOURS | H22: OUR COST | I22: NET PROFIT | J22: % Profit
A23: =IFERROR(INDEX(SCOPE!$U$4:$U$23,MATCH(1,SCOPE!$T$4:$T$23,0)),"") -> PM/EC | B23: =IFERROR(INDEX(SCOPE!$P$4:$P$23,MATCH(1,SCOPE!$T$4:$T$23,0)),"") -> PLANNING, TIMELINE & COMMUNICATIONS | C23: =IF(OR(B23="",D23=0),"",E23/D23) -> 102.48 | D23: =IFERROR(INDEX(SCOPE!$Q$4:$Q$23,MATCH(1,SCOPE!$T$4:$T$23,0)),"") -> 125 | E23: =IFERROR(INDEX(SCOPE!$R$4:$R$23,MATCH(1,SCOPE!$T$4:$T$23,0)),"") -> 12810 | F23: =IF(OR(B23="",G23=0),"",H23/G23) -> 67.488 | G23: =IF(B23="","",D23) -> 125 | H23: =IFERROR(INDEX(SCOPE!$S$4:$S$23,MATCH(1,SCOPE!$T$4:$T$23,0)),"") -> 8436 | I23: =IF(B23="","",E23-H23) -> 4374 | J23: =IF(OR(B23="",E23=0),"",I23/E23) -> 0.34145199
A24: =IFERROR(INDEX(SCOPE!$U$4:$U$23,MATCH(2,SCOPE!$T$4:$T$23,0)),"") -> PM | B24: =IFERROR(INDEX(SCOPE!$P$4:$P$23,MATCH(2,SCOPE!$T$4:$T$23,0)),"") -> VENUE MANAGEMENT | C24: =IF(OR(B24="",D24=0),"",E24/D24) -> 90 | D24: =IFERROR(INDEX(SCOPE!$Q$4:$Q$23,MATCH(2,SCOPE!$T$4:$T$23,0)),"") -> 40 | E24: =IFERROR(INDEX(SCOPE!$R$4:$R$23,MATCH(2,SCOPE!$T$4:$T$23,0)),"") -> 3600 | F24: =IF(OR(B24="",G24=0),"",H24/G24) -> 60 | G24: =IF(B24="","",D24) -> 40 | H24: =IFERROR(INDEX(SCOPE!$S$4:$S$23,MATCH(2,SCOPE!$T$4:$T$23,0)),"") -> 2400 | I24: =IF(B24="","",E24-H24) -> 1200 | J24: =IF(OR(B24="",E24=0),"",I24/E24) -> 0.33333333
A25: =IFERROR(INDEX(SCOPE!$U$4:$U$23,MATCH(3,SCOPE!$T$4:$T$23,0)),"") -> PM | B25: =IFERROR(INDEX(SCOPE!$P$4:$P$23,MATCH(3,SCOPE!$T$4:$T$23,0)),"") -> EVENT BRANDING | C25: =IF(OR(B25="",D25=0),"",E25/D25) -> 90 | D25: =IFERROR(INDEX(SCOPE!$Q$4:$Q$23,MATCH(3,SCOPE!$T$4:$T$23,0)),"") -> 45 | E25: =IFERROR(INDEX(SCOPE!$R$4:$R$23,MATCH(3,SCOPE!$T$4:$T$23,0)),"") -> 4050 | F25: =IF(OR(B25="",G25=0),"",H25/G25) -> 60 | G25: =IF(B25="","",D25) -> 45 | H25: =IFERROR(INDEX(SCOPE!$S$4:$S$23,MATCH(3,SCOPE!$T$4:$T$23,0)),"") -> 2700 | I25: =IF(B25="","",E25-H25) -> 1350 | J25: =IF(OR(B25="",E25=0),"",I25/E25) -> 0.33333333
A26: =IFERROR(INDEX(SCOPE!$U$4:$U$23,MATCH(4,SCOPE!$T$4:$T$23,0)),"") -> PM | B26: =IFERROR(INDEX(SCOPE!$P$4:$P$23,MATCH(4,SCOPE!$T$4:$T$23,0)),"") -> FOOD & BEVERAGE | C26: =IF(OR(B26="",D26=0),"",E26/D26) -> 90 | D26: =IFERROR(INDEX(SCOPE!$Q$4:$Q$23,MATCH(4,SCOPE!$T$4:$T$23,0)),"") -> 34 | E26: =IFERROR(INDEX(SCOPE!$R$4:$R$23,MATCH(4,SCOPE!$T$4:$T$23,0)),"") -> 3060 | F26: =IF(OR(B26="",G26=0),"",H26/G26) -> 60 | G26: =IF(B26="","",D26) -> 34 | H26: =IFERROR(INDEX(SCOPE!$S$4:$S$23,MATCH(4,SCOPE!$T$4:$T$23,0)),"") -> 2040 | I26: =IF(B26="","",E26-H26) -> 1020 | J26: =IF(OR(B26="",E26=0),"",I26/E26) -> 0.33333333
A27: =IFERROR(INDEX(SCOPE!$U$4:$U$23,MATCH(5,SCOPE!$T$4:$T$23,0)),"") -> EC | B27: =IFERROR(INDEX(SCOPE!$P$4:$P$23,MATCH(5,SCOPE!$T$4:$T$23,0)),"") -> REGISTRATION | C27: =IF(OR(B27="",D27=0),"",E27/D27) -> 65 | D27: =IFERROR(INDEX(SCOPE!$Q$4:$Q$23,MATCH(5,SCOPE!$T$4:$T$23,0)),"") -> 82 | E27: =IFERROR(INDEX(SCOPE!$R$4:$R$23,MATCH(5,SCOPE!$T$4:$T$23,0)),"") -> 5330 | F27: =IF(OR(B27="",G27=0),"",H27/G27) -> 42 | G27: =IF(B27="","",D27) -> 82 | H27: =IFERROR(INDEX(SCOPE!$S$4:$S$23,MATCH(5,SCOPE!$T$4:$T$23,0)),"") -> 3444 | I27: =IF(B27="","",E27-H27) -> 1886 | J27: =IF(OR(B27="",E27=0),"",I27/E27) -> 0.35384615
A28: =IFERROR(INDEX(SCOPE!$U$4:$U$23,MATCH(6,SCOPE!$T$4:$T$23,0)),"") -> EC | B28: =IFERROR(INDEX(SCOPE!$P$4:$P$23,MATCH(6,SCOPE!$T$4:$T$23,0)),"") -> THIRD PARTY VENDORS | C28: =IF(OR(B28="",D28=0),"",E28/D28) -> 65 | D28: =IFERROR(INDEX(SCOPE!$Q$4:$Q$23,MATCH(6,SCOPE!$T$4:$T$23,0)),"") -> 40 | E28: =IFERROR(INDEX(SCOPE!$R$4:$R$23,MATCH(6,SCOPE!$T$4:$T$23,0)),"") -> 2600 | F28: =IF(OR(B28="",G28=0),"",H28/G28) -> 42 | G28: =IF(B28="","",D28) -> 40 | H28: =IFERROR(INDEX(SCOPE!$S$4:$S$23,MATCH(6,SCOPE!$T$4:$T$23,0)),"") -> 1680 | I28: =IF(B28="","",E28-H28) -> 920 | J28: =IF(OR(B28="",E28=0),"",I28/E28) -> 0.35384615
A29: =IFERROR(INDEX(SCOPE!$U$4:$U$23,MATCH(7,SCOPE!$T$4:$T$23,0)),"") -> PM | B29: =IFERROR(INDEX(SCOPE!$P$4:$P$23,MATCH(7,SCOPE!$T$4:$T$23,0)),"") -> STAFF MANAGEMENT | C29: =IF(OR(B29="",D29=0),"",E29/D29) -> 90 | D29: =IFERROR(INDEX(SCOPE!$Q$4:$Q$23,MATCH(7,SCOPE!$T$4:$T$23,0)),"") -> 14 | E29: =IFERROR(INDEX(SCOPE!$R$4:$R$23,MATCH(7,SCOPE!$T$4:$T$23,0)),"") -> 1260 | F29: =IF(OR(B29="",G29=0),"",H29/G29) -> 60 | G29: =IF(B29="","",D29) -> 14 | H29: =IFERROR(INDEX(SCOPE!$S$4:$S$23,MATCH(7,SCOPE!$T$4:$T$23,0)),"") -> 840 | I29: =IF(B29="","",E29-H29) -> 420 | J29: =IF(OR(B29="",E29=0),"",I29/E29) -> 0.33333333
A30: =IFERROR(INDEX(SCOPE!$U$4:$U$23,MATCH(8,SCOPE!$T$4:$T$23,0)),"") -> EC | B30: =IFERROR(INDEX(SCOPE!$P$4:$P$23,MATCH(8,SCOPE!$T$4:$T$23,0)),"") -> SPONSORSHIPS | C30: =IF(OR(B30="",D30=0),"",E30/D30) -> 65 | D30: =IFERROR(INDEX(SCOPE!$Q$4:$Q$23,MATCH(8,SCOPE!$T$4:$T$23,0)),"") -> 32 | E30: =IFERROR(INDEX(SCOPE!$R$4:$R$23,MATCH(8,SCOPE!$T$4:$T$23,0)),"") -> 2080 | F30: =IF(OR(B30="",G30=0),"",H30/G30) -> 42 | G30: =IF(B30="","",D30) -> 32 | H30: =IFERROR(INDEX(SCOPE!$S$4:$S$23,MATCH(8,SCOPE!$T$4:$T$23,0)),"") -> 1344 | I30: =IF(B30="","",E30-H30) -> 736 | J30: =IF(OR(B30="",E30=0),"",I30/E30) -> 0.35384615
A31: =IFERROR(INDEX(SCOPE!$U$4:$U$23,MATCH(9,SCOPE!$T$4:$T$23,0)),"") -> PM | B31: =IFERROR(INDEX(SCOPE!$P$4:$P$23,MATCH(9,SCOPE!$T$4:$T$23,0)),"") -> PROGRAMMING | C31: =IF(OR(B31="",D31=0),"",E31/D31) -> 90 | D31: =IFERROR(INDEX(SCOPE!$Q$4:$Q$23,MATCH(9,SCOPE!$T$4:$T$23,0)),"") -> 63 | E31: =IFERROR(INDEX(SCOPE!$R$4:$R$23,MATCH(9,SCOPE!$T$4:$T$23,0)),"") -> 5670 | F31: =IF(OR(B31="",G31=0),"",H31/G31) -> 60 | G31: =IF(B31="","",D31) -> 63 | H31: =IFERROR(INDEX(SCOPE!$S$4:$S$23,MATCH(9,SCOPE!$T$4:$T$23,0)),"") -> 3780 | I31: =IF(B31="","",E31-H31) -> 1890 | J31: =IF(OR(B31="",E31=0),"",I31/E31) -> 0.33333333
A32: =IFERROR(INDEX(SCOPE!$U$4:$U$23,MATCH(10,SCOPE!$T$4:$T$23,0)),"") -> PM | B32: =IFERROR(INDEX(SCOPE!$P$4:$P$23,MATCH(10,SCOPE!$T$4:$T$23,0)),"") -> FINANCIAL MANAGEMENT | C32: =IF(OR(B32="",D32=0),"",E32/D32) -> 90 | D32: =IFERROR(INDEX(SCOPE!$Q$4:$Q$23,MATCH(10,SCOPE!$T$4:$T$23,0)),"") -> 18 | E32: =IFERROR(INDEX(SCOPE!$R$4:$R$23,MATCH(10,SCOPE!$T$4:$T$23,0)),"") -> 1620 | F32: =IF(OR(B32="",G32=0),"",H32/G32) -> 60 | G32: =IF(B32="","",D32) -> 18 | H32: =IFERROR(INDEX(SCOPE!$S$4:$S$23,MATCH(10,SCOPE!$T$4:$T$23,0)),"") -> 1080 | I32: =IF(B32="","",E32-H32) -> 540 | J32: =IF(OR(B32="",E32=0),"",I32/E32) -> 0.33333333
A33: =IFERROR(INDEX(SCOPE!$U$4:$U$23,MATCH(11,SCOPE!$T$4:$T$23,0)),"") -> PM | B33: =IFERROR(INDEX(SCOPE!$P$4:$P$23,MATCH(11,SCOPE!$T$4:$T$23,0)),"") -> EXHIBIT MANAGEMENT | C33: =IF(OR(B33="",D33=0),"",E33/D33) -> 90 | D33: =IFERROR(INDEX(SCOPE!$Q$4:$Q$23,MATCH(11,SCOPE!$T$4:$T$23,0)),"") -> 60 | E33: =IFERROR(INDEX(SCOPE!$R$4:$R$23,MATCH(11,SCOPE!$T$4:$T$23,0)),"") -> 5400 | F33: =IF(OR(B33="",G33=0),"",H33/G33) -> 60 | G33: =IF(B33="","",D33) -> 60 | H33: =IFERROR(INDEX(SCOPE!$S$4:$S$23,MATCH(11,SCOPE!$T$4:$T$23,0)),"") -> 3600 | I33: =IF(B33="","",E33-H33) -> 1800 | J33: =IF(OR(B33="",E33=0),"",I33/E33) -> 0.33333333
A34: =IFERROR(INDEX(SCOPE!$U$4:$U$23,MATCH(12,SCOPE!$T$4:$T$23,0)),"") -> PM | B34: =IFERROR(INDEX(SCOPE!$P$4:$P$23,MATCH(12,SCOPE!$T$4:$T$23,0)),"") -> POST-EVENT | C34: =IF(OR(B34="",D34=0),"",E34/D34) -> 90 | D34: =IFERROR(INDEX(SCOPE!$Q$4:$Q$23,MATCH(12,SCOPE!$T$4:$T$23,0)),"") -> 15 | E34: =IFERROR(INDEX(SCOPE!$R$4:$R$23,MATCH(12,SCOPE!$T$4:$T$23,0)),"") -> 1350 | F34: =IF(OR(B34="",G34=0),"",H34/G34) -> 60 | G34: =IF(B34="","",D34) -> 15 | H34: =IFERROR(INDEX(SCOPE!$S$4:$S$23,MATCH(12,SCOPE!$T$4:$T$23,0)),"") -> 900 | I34: =IF(B34="","",E34-H34) -> 450 | J34: =IF(OR(B34="",E34=0),"",I34/E34) -> 0.33333333
A35: =IFERROR(INDEX(SCOPE!$U$4:$U$23,MATCH(13,SCOPE!$T$4:$T$23,0)),"") | B35: =IFERROR(INDEX(SCOPE!$P$4:$P$23,MATCH(13,SCOPE!$T$4:$T$23,0)),"") | C35: =IF(OR(B35="",D35=0),"",E35/D35) | D35: =IFERROR(INDEX(SCOPE!$Q$4:$Q$23,MATCH(13,SCOPE!$T$4:$T$23,0)),"") | E35: =IFERROR(INDEX(SCOPE!$R$4:$R$23,MATCH(13,SCOPE!$T$4:$T$23,0)),"") | F35: =IF(OR(B35="",G35=0),"",H35/G35) | G35: =IF(B35="","",D35) | H35: =IFERROR(INDEX(SCOPE!$S$4:$S$23,MATCH(13,SCOPE!$T$4:$T$23,0)),"") | I35: =IF(B35="","",E35-H35) | J35: =IF(OR(B35="",E35=0),"",I35/E35)
A36: =IFERROR(INDEX(SCOPE!$U$4:$U$23,MATCH(14,SCOPE!$T$4:$T$23,0)),"") | B36: =IFERROR(INDEX(SCOPE!$P$4:$P$23,MATCH(14,SCOPE!$T$4:$T$23,0)),"") | C36: =IF(OR(B36="",D36=0),"",E36/D36) | D36: =IFERROR(INDEX(SCOPE!$Q$4:$Q$23,MATCH(14,SCOPE!$T$4:$T$23,0)),"") | E36: =IFERROR(INDEX(SCOPE!$R$4:$R$23,MATCH(14,SCOPE!$T$4:$T$23,0)),"") | F36: =IF(OR(B36="",G36=0),"",H36/G36) | G36: =IF(B36="","",D36) | H36: =IFERROR(INDEX(SCOPE!$S$4:$S$23,MATCH(14,SCOPE!$T$4:$T$23,0)),"") | I36: =IF(B36="","",E36-H36) | J36: =IF(OR(B36="",E36=0),"",I36/E36)
A37: =IFERROR(INDEX(SCOPE!$U$4:$U$23,MATCH(15,SCOPE!$T$4:$T$23,0)),"") | B37: =IFERROR(INDEX(SCOPE!$P$4:$P$23,MATCH(15,SCOPE!$T$4:$T$23,0)),"") | C37: =IF(OR(B37="",D37=0),"",E37/D37) | D37: =IFERROR(INDEX(SCOPE!$Q$4:$Q$23,MATCH(15,SCOPE!$T$4:$T$23,0)),"") | E37: =IFERROR(INDEX(SCOPE!$R$4:$R$23,MATCH(15,SCOPE!$T$4:$T$23,0)),"") | F37: =IF(OR(B37="",G37=0),"",H37/G37) | G37: =IF(B37="","",D37) | H37: =IFERROR(INDEX(SCOPE!$S$4:$S$23,MATCH(15,SCOPE!$T$4:$T$23,0)),"") | I37: =IF(B37="","",E37-H37) | J37: =IF(OR(B37="",E37=0),"",I37/E37)
A38: =IFERROR(INDEX(SCOPE!$U$4:$U$23,MATCH(16,SCOPE!$T$4:$T$23,0)),"") | B38: =IFERROR(INDEX(SCOPE!$P$4:$P$23,MATCH(16,SCOPE!$T$4:$T$23,0)),"") | C38: =IF(OR(B38="",D38=0),"",E38/D38) | D38: =IFERROR(INDEX(SCOPE!$Q$4:$Q$23,MATCH(16,SCOPE!$T$4:$T$23,0)),"") | E38: =IFERROR(INDEX(SCOPE!$R$4:$R$23,MATCH(16,SCOPE!$T$4:$T$23,0)),"") | F38: =IF(OR(B38="",G38=0),"",H38/G38) | G38: =IF(B38="","",D38) | H38: =IFERROR(INDEX(SCOPE!$S$4:$S$23,MATCH(16,SCOPE!$T$4:$T$23,0)),"") | I38: =IF(B38="","",E38-H38) | J38: =IF(OR(B38="",E38=0),"",I38/E38)
A39: =IFERROR(INDEX(SCOPE!$U$4:$U$23,MATCH(17,SCOPE!$T$4:$T$23,0)),"") | B39: =IFERROR(INDEX(SCOPE!$P$4:$P$23,MATCH(17,SCOPE!$T$4:$T$23,0)),"") | C39: =IF(OR(B39="",D39=0),"",E39/D39) | D39: =IFERROR(INDEX(SCOPE!$Q$4:$Q$23,MATCH(17,SCOPE!$T$4:$T$23,0)),"") | E39: =IFERROR(INDEX(SCOPE!$R$4:$R$23,MATCH(17,SCOPE!$T$4:$T$23,0)),"") | F39: =IF(OR(B39="",G39=0),"",H39/G39) | G39: =IF(B39="","",D39) | H39: =IFERROR(INDEX(SCOPE!$S$4:$S$23,MATCH(17,SCOPE!$T$4:$T$23,0)),"") | I39: =IF(B39="","",E39-H39) | J39: =IF(OR(B39="",E39=0),"",I39/E39)
A40: =IFERROR(INDEX(SCOPE!$U$4:$U$23,MATCH(18,SCOPE!$T$4:$T$23,0)),"") | B40: =IFERROR(INDEX(SCOPE!$P$4:$P$23,MATCH(18,SCOPE!$T$4:$T$23,0)),"") | C40: =IF(OR(B40="",D40=0),"",E40/D40) | D40: =IFERROR(INDEX(SCOPE!$Q$4:$Q$23,MATCH(18,SCOPE!$T$4:$T$23,0)),"") | E40: =IFERROR(INDEX(SCOPE!$R$4:$R$23,MATCH(18,SCOPE!$T$4:$T$23,0)),"") | F40: =IF(OR(B40="",G40=0),"",H40/G40) | G40: =IF(B40="","",D40) | H40: =IFERROR(INDEX(SCOPE!$S$4:$S$23,MATCH(18,SCOPE!$T$4:$T$23,0)),"") | I40: =IF(B40="","",E40-H40) | J40: =IF(OR(B40="",E40=0),"",I40/E40)
A41: =IFERROR(INDEX(SCOPE!$U$4:$U$23,MATCH(19,SCOPE!$T$4:$T$23,0)),"") | B41: =IFERROR(INDEX(SCOPE!$P$4:$P$23,MATCH(19,SCOPE!$T$4:$T$23,0)),"") | C41: =IF(OR(B41="",D41=0),"",E41/D41) | D41: =IFERROR(INDEX(SCOPE!$Q$4:$Q$23,MATCH(19,SCOPE!$T$4:$T$23,0)),"") | E41: =IFERROR(INDEX(SCOPE!$R$4:$R$23,MATCH(19,SCOPE!$T$4:$T$23,0)),"") | F41: =IF(OR(B41="",G41=0),"",H41/G41) | G41: =IF(B41="","",D41) | H41: =IFERROR(INDEX(SCOPE!$S$4:$S$23,MATCH(19,SCOPE!$T$4:$T$23,0)),"") | I41: =IF(B41="","",E41-H41) | J41: =IF(OR(B41="",E41=0),"",I41/E41)
A42: =IFERROR(INDEX(SCOPE!$U$4:$U$23,MATCH(20,SCOPE!$T$4:$T$23,0)),"") | B42: =IFERROR(INDEX(SCOPE!$P$4:$P$23,MATCH(20,SCOPE!$T$4:$T$23,0)),"") | C42: =IF(OR(B42="",D42=0),"",E42/D42) | D42: =IFERROR(INDEX(SCOPE!$Q$4:$Q$23,MATCH(20,SCOPE!$T$4:$T$23,0)),"") | E42: =IFERROR(INDEX(SCOPE!$R$4:$R$23,MATCH(20,SCOPE!$T$4:$T$23,0)),"") | F42: =IF(OR(B42="",G42=0),"",H42/G42) | G42: =IF(B42="","",D42) | H42: =IFERROR(INDEX(SCOPE!$S$4:$S$23,MATCH(20,SCOPE!$T$4:$T$23,0)),"") | I42: =IF(B42="","",E42-H42) | J42: =IF(OR(B42="",E42=0),"",I42/E42)
B43: TOTALS | D43: =SUM(D23:D42) -> 568 | E43: =SUM(E23:E42) -> 48830 | G43: =SUM(G23:G42) -> 568 | H43: =SUM(H23:H42) -> 32244 | I43: =SUM(I23:I42) -> 16586 | J43: =IF(E43=0,"",I43/E43) -> 0.33966824
B45: ONSITE MANAGEMENT
B46: SCOPE OF WORK | C46: CLIENT RATE | D46: HOURS | E46: CLIENT COST | F46: OUR RATE | G46: HOURS | H46: OUR COST | I46: NET PROFIT | J46: % Profit
A47: =IF(1<=INPUTS!$C$27,"PM","") -> PM | B47: =IF(1<=INPUTS!$C$27,INPUTS!$C$55,"") -> Project Manager | C47: =IF(1<=INPUTS!$C$27,INPUTS!$C$37,"") -> 100 | D47: =IF(1<=INPUTS!$C$27,(INPUTS!$C$18+INPUTS!$C$19)*INPUTS!$C$42+INPUTS!$C$20*INPUTS!$C$45,"") -> 48 | E47: =IF(B47="","",C47*D47) -> 4800 | F47: =IF(1<=INPUTS!$C$27,INPUTS!$C$33,"") -> 60 | G47: =IF(B47="","",D47) -> 48 | H47: =IF(B47="","",F47*G47) -> 2880 | I47: =IF(B47="","",E47-H47) -> 1920 | J47: =IF(OR(B47="",E47=0),"",I47/E47) -> 0.4
A48: =IF(2<=INPUTS!$C$27,"PM","") -> PM | B48: =IF(2<=INPUTS!$C$27,INPUTS!$C$56,"") -> Event Manager | C48: =IF(2<=INPUTS!$C$27,INPUTS!$C$37,"") -> 100 | D48: =IF(2<=INPUTS!$C$27,(INPUTS!$C$18+INPUTS!$C$19)*INPUTS!$C$42+INPUTS!$C$20*INPUTS!$C$45,"") -> 48 | E48: =IF(B48="","",C48*D48) -> 4800 | F48: =IF(2<=INPUTS!$C$27,INPUTS!$C$33,"") -> 60 | G48: =IF(B48="","",D48) -> 48 | H48: =IF(B48="","",F48*G48) -> 2880 | I48: =IF(B48="","",E48-H48) -> 1920 | J48: =IF(OR(B48="",E48=0),"",I48/E48) -> 0.4
A49: =IF(3<=INPUTS!$C$27,"PM","") -> PM | B49: =IF(3<=INPUTS!$C$27,INPUTS!$C$57,"") -> Executive Producer | C49: =IF(3<=INPUTS!$C$27,INPUTS!$C$37,"") -> 100 | D49: =IF(3<=INPUTS!$C$27,(INPUTS!$C$18+INPUTS!$C$19)*INPUTS!$C$42+INPUTS!$C$20*INPUTS!$C$45,"") -> 48 | E49: =IF(B49="","",C49*D49) -> 4800 | F49: =IF(3<=INPUTS!$C$27,INPUTS!$C$33,"") -> 60 | G49: =IF(B49="","",D49) -> 48 | H49: =IF(B49="","",F49*G49) -> 2880 | I49: =IF(B49="","",E49-H49) -> 1920 | J49: =IF(OR(B49="",E49=0),"",I49/E49) -> 0.4
A50: =IF(4<=INPUTS!$C$27,"PM","") | B50: =IF(4<=INPUTS!$C$27,INPUTS!$C$58,"") | C50: =IF(4<=INPUTS!$C$27,INPUTS!$C$37,"") | D50: =IF(4<=INPUTS!$C$27,(INPUTS!$C$18+INPUTS!$C$19)*INPUTS!$C$42+INPUTS!$C$20*INPUTS!$C$45,"") | E50: =IF(B50="","",C50*D50) | F50: =IF(4<=INPUTS!$C$27,INPUTS!$C$33,"") | G50: =IF(B50="","",D50) | H50: =IF(B50="","",F50*G50) | I50: =IF(B50="","",E50-H50) | J50: =IF(OR(B50="",E50=0),"",I50/E50)
A51: =IF(5<=INPUTS!$C$27,"PM","") | B51: =IF(5<=INPUTS!$C$27,INPUTS!$C$59,"") | C51: =IF(5<=INPUTS!$C$27,INPUTS!$C$37,"") | D51: =IF(5<=INPUTS!$C$27,(INPUTS!$C$18+INPUTS!$C$19)*INPUTS!$C$42+INPUTS!$C$20*INPUTS!$C$45,"") | E51: =IF(B51="","",C51*D51) | F51: =IF(5<=INPUTS!$C$27,INPUTS!$C$33,"") | G51: =IF(B51="","",D51) | H51: =IF(B51="","",F51*G51) | I51: =IF(B51="","",E51-H51) | J51: =IF(OR(B51="",E51=0),"",I51/E51)
A52: =IF(6<=INPUTS!$C$27,"PM","") | B52: =IF(6<=INPUTS!$C$27,INPUTS!$C$60,"") | C52: =IF(6<=INPUTS!$C$27,INPUTS!$C$37,"") | D52: =IF(6<=INPUTS!$C$27,(INPUTS!$C$18+INPUTS!$C$19)*INPUTS!$C$42+INPUTS!$C$20*INPUTS!$C$45,"") | E52: =IF(B52="","",C52*D52) | F52: =IF(6<=INPUTS!$C$27,INPUTS!$C$33,"") | G52: =IF(B52="","",D52) | H52: =IF(B52="","",F52*G52) | I52: =IF(B52="","",E52-H52) | J52: =IF(OR(B52="",E52=0),"",I52/E52)
A53: =IF(7<=INPUTS!$C$27,"PM","") | B53: =IF(7<=INPUTS!$C$27,INPUTS!$C$61,"") | C53: =IF(7<=INPUTS!$C$27,INPUTS!$C$37,"") | D53: =IF(7<=INPUTS!$C$27,(INPUTS!$C$18+INPUTS!$C$19)*INPUTS!$C$42+INPUTS!$C$20*INPUTS!$C$45,"") | E53: =IF(B53="","",C53*D53) | F53: =IF(7<=INPUTS!$C$27,INPUTS!$C$33,"") | G53: =IF(B53="","",D53) | H53: =IF(B53="","",F53*G53) | I53: =IF(B53="","",E53-H53) | J53: =IF(OR(B53="",E53=0),"",I53/E53)
A54: =IF(8<=INPUTS!$C$27,"PM","") | B54: =IF(8<=INPUTS!$C$27,INPUTS!$C$62,"") | C54: =IF(8<=INPUTS!$C$27,INPUTS!$C$37,"") | D54: =IF(8<=INPUTS!$C$27,(INPUTS!$C$18+INPUTS!$C$19)*INPUTS!$C$42+INPUTS!$C$20*INPUTS!$C$45,"") | E54: =IF(B54="","",C54*D54) | F54: =IF(8<=INPUTS!$C$27,INPUTS!$C$33,"") | G54: =IF(B54="","",D54) | H54: =IF(B54="","",F54*G54) | I54: =IF(B54="","",E54-H54) | J54: =IF(OR(B54="",E54=0),"",I54/E54)
A55: =IF(9<=INPUTS!$C$27,"PM","") | B55: =IF(9<=INPUTS!$C$27,INPUTS!$C$63,"") | C55: =IF(9<=INPUTS!$C$27,INPUTS!$C$37,"") | D55: =IF(9<=INPUTS!$C$27,(INPUTS!$C$18+INPUTS!$C$19)*INPUTS!$C$42+INPUTS!$C$20*INPUTS!$C$45,"") | E55: =IF(B55="","",C55*D55) | F55: =IF(9<=INPUTS!$C$27,INPUTS!$C$33,"") | G55: =IF(B55="","",D55) | H55: =IF(B55="","",F55*G55) | I55: =IF(B55="","",E55-H55) | J55: =IF(OR(B55="",E55=0),"",I55/E55)
A56: =IF(10<=INPUTS!$C$27,"PM","") | B56: =IF(10<=INPUTS!$C$27,INPUTS!$C$64,"") | C56: =IF(10<=INPUTS!$C$27,INPUTS!$C$37,"") | D56: =IF(10<=INPUTS!$C$27,(INPUTS!$C$18+INPUTS!$C$19)*INPUTS!$C$42+INPUTS!$C$20*INPUTS!$C$45,"") | E56: =IF(B56="","",C56*D56) | F56: =IF(10<=INPUTS!$C$27,INPUTS!$C$33,"") | G56: =IF(B56="","",D56) | H56: =IF(B56="","",F56*G56) | I56: =IF(B56="","",E56-H56) | J56: =IF(OR(B56="",E56=0),"",I56/E56)
A57: =IF(1<=INPUTS!$C$28,"EC","") -> EC | B57: =IF(1<=INPUTS!$C$28,INPUTS!$C$66,"") -> Event Coordinator | C57: =IF(1<=INPUTS!$C$28,INPUTS!$C$38,"") -> 65 | D57: =IF(1<=INPUTS!$C$28,(INPUTS!$C$18+INPUTS!$C$19)*INPUTS!$C$43+INPUTS!$C$20*INPUTS!$C$45,"") -> 32 | E57: =IF(B57="","",C57*D57) -> 2080 | F57: =IF(1<=INPUTS!$C$28,INPUTS!$C$34,"") -> 42 | G57: =IF(B57="","",D57) -> 32 | H57: =IF(B57="","",F57*G57) -> 1344 | I57: =IF(B57="","",E57-H57) -> 736 | J57: =IF(OR(B57="",E57=0),"",I57/E57) -> 0.35384615
A58: =IF(2<=INPUTS!$C$28,"EC","") -> EC | B58: =IF(2<=INPUTS!$C$28,INPUTS!$C$67,"") -> Registration Coordinator | C58: =IF(2<=INPUTS!$C$28,INPUTS!$C$38,"") -> 65 | D58: =IF(2<=INPUTS!$C$28,(INPUTS!$C$18+INPUTS!$C$19)*INPUTS!$C$43+INPUTS!$C$20*INPUTS!$C$45,"") -> 32 | E58: =IF(B58="","",C58*D58) -> 2080 | F58: =IF(2<=INPUTS!$C$28,INPUTS!$C$34,"") -> 42 | G58: =IF(B58="","",D58) -> 32 | H58: =IF(B58="","",F58*G58) -> 1344 | I58: =IF(B58="","",E58-H58) -> 736 | J58: =IF(OR(B58="",E58=0),"",I58/E58) -> 0.35384615
A59: =IF(3<=INPUTS!$C$28,"EC","") | B59: =IF(3<=INPUTS!$C$28,INPUTS!$C$68,"") | C59: =IF(3<=INPUTS!$C$28,INPUTS!$C$38,"") | D59: =IF(3<=INPUTS!$C$28,(INPUTS!$C$18+INPUTS!$C$19)*INPUTS!$C$43+INPUTS!$C$20*INPUTS!$C$45,"") | E59: =IF(B59="","",C59*D59) | F59: =IF(3<=INPUTS!$C$28,INPUTS!$C$34,"") | G59: =IF(B59="","",D59) | H59: =IF(B59="","",F59*G59) | I59: =IF(B59="","",E59-H59) | J59: =IF(OR(B59="",E59=0),"",I59/E59)
A60: =IF(4<=INPUTS!$C$28,"EC","") | B60: =IF(4<=INPUTS!$C$28,INPUTS!$C$69,"") | C60: =IF(4<=INPUTS!$C$28,INPUTS!$C$38,"") | D60: =IF(4<=INPUTS!$C$28,(INPUTS!$C$18+INPUTS!$C$19)*INPUTS!$C$43+INPUTS!$C$20*INPUTS!$C$45,"") | E60: =IF(B60="","",C60*D60) | F60: =IF(4<=INPUTS!$C$28,INPUTS!$C$34,"") | G60: =IF(B60="","",D60) | H60: =IF(B60="","",F60*G60) | I60: =IF(B60="","",E60-H60) | J60: =IF(OR(B60="",E60=0),"",I60/E60)
A61: =IF(5<=INPUTS!$C$28,"EC","") | B61: =IF(5<=INPUTS!$C$28,INPUTS!$C$70,"") | C61: =IF(5<=INPUTS!$C$28,INPUTS!$C$38,"") | D61: =IF(5<=INPUTS!$C$28,(INPUTS!$C$18+INPUTS!$C$19)*INPUTS!$C$43+INPUTS!$C$20*INPUTS!$C$45,"") | E61: =IF(B61="","",C61*D61) | F61: =IF(5<=INPUTS!$C$28,INPUTS!$C$34,"") | G61: =IF(B61="","",D61) | H61: =IF(B61="","",F61*G61) | I61: =IF(B61="","",E61-H61) | J61: =IF(OR(B61="",E61=0),"",I61/E61)
A62: =IF(6<=INPUTS!$C$28,"EC","") | B62: =IF(6<=INPUTS!$C$28,INPUTS!$C$71,"") | C62: =IF(6<=INPUTS!$C$28,INPUTS!$C$38,"") | D62: =IF(6<=INPUTS!$C$28,(INPUTS!$C$18+INPUTS!$C$19)*INPUTS!$C$43+INPUTS!$C$20*INPUTS!$C$45,"") | E62: =IF(B62="","",C62*D62) | F62: =IF(6<=INPUTS!$C$28,INPUTS!$C$34,"") | G62: =IF(B62="","",D62) | H62: =IF(B62="","",F62*G62) | I62: =IF(B62="","",E62-H62) | J62: =IF(OR(B62="",E62=0),"",I62/E62)
A63: =IF(7<=INPUTS!$C$28,"EC","") | B63: =IF(7<=INPUTS!$C$28,INPUTS!$C$72,"") | C63: =IF(7<=INPUTS!$C$28,INPUTS!$C$38,"") | D63: =IF(7<=INPUTS!$C$28,(INPUTS!$C$18+INPUTS!$C$19)*INPUTS!$C$43+INPUTS!$C$20*INPUTS!$C$45,"") | E63: =IF(B63="","",C63*D63) | F63: =IF(7<=INPUTS!$C$28,INPUTS!$C$34,"") | G63: =IF(B63="","",D63) | H63: =IF(B63="","",F63*G63) | I63: =IF(B63="","",E63-H63) | J63: =IF(OR(B63="",E63=0),"",I63/E63)
A64: =IF(8<=INPUTS!$C$28,"EC","") | B64: =IF(8<=INPUTS!$C$28,INPUTS!$C$73,"") | C64: =IF(8<=INPUTS!$C$28,INPUTS!$C$38,"") | D64: =IF(8<=INPUTS!$C$28,(INPUTS!$C$18+INPUTS!$C$19)*INPUTS!$C$43+INPUTS!$C$20*INPUTS!$C$45,"") | E64: =IF(B64="","",C64*D64) | F64: =IF(8<=INPUTS!$C$28,INPUTS!$C$34,"") | G64: =IF(B64="","",D64) | H64: =IF(B64="","",F64*G64) | I64: =IF(B64="","",E64-H64) | J64: =IF(OR(B64="",E64=0),"",I64/E64)
A65: =IF(9<=INPUTS!$C$28,"EC","") | B65: =IF(9<=INPUTS!$C$28,INPUTS!$C$74,"") | C65: =IF(9<=INPUTS!$C$28,INPUTS!$C$38,"") | D65: =IF(9<=INPUTS!$C$28,(INPUTS!$C$18+INPUTS!$C$19)*INPUTS!$C$43+INPUTS!$C$20*INPUTS!$C$45,"") | E65: =IF(B65="","",C65*D65) | F65: =IF(9<=INPUTS!$C$28,INPUTS!$C$34,"") | G65: =IF(B65="","",D65) | H65: =IF(B65="","",F65*G65) | I65: =IF(B65="","",E65-H65) | J65: =IF(OR(B65="",E65=0),"",I65/E65)
A66: =IF(10<=INPUTS!$C$28,"EC","") | B66: =IF(10<=INPUTS!$C$28,INPUTS!$C$75,"") | C66: =IF(10<=INPUTS!$C$28,INPUTS!$C$38,"") | D66: =IF(10<=INPUTS!$C$28,(INPUTS!$C$18+INPUTS!$C$19)*INPUTS!$C$43+INPUTS!$C$20*INPUTS!$C$45,"") | E66: =IF(B66="","",C66*D66) | F66: =IF(10<=INPUTS!$C$28,INPUTS!$C$34,"") | G66: =IF(B66="","",D66) | H66: =IF(B66="","",F66*G66) | I66: =IF(B66="","",E66-H66) | J66: =IF(OR(B66="",E66=0),"",I66/E66)
A67: =IF(INPUTS!$C$28=0,"","EC") -> EC | B67: =IF(INPUTS!$C$28=0,"","Coordinator Overtime ("&TEXT(INPUTS!$C$28,"0")&" x "&TEXT(INPUTS!$C$44,"0")&" hrs x "&TEXT(INPUTS!$C$18+INPUTS!$C$19,"0")&" days)") -> Coordinator Overtime (2 x 2 hrs x 4 days) | C67: =IF(INPUTS!$C$28=0,"",INPUTS!$C$38*INPUTS!$C$39) -> 97.5 | D67: =IF(INPUTS!$C$28=0,"",INPUTS!$C$28*(INPUTS!$C$18+INPUTS!$C$19)*INPUTS!$C$44) -> 16 | E67: =IF(B67="","",C67*D67) -> 1560 | F67: =IF(INPUTS!$C$28=0,"",INPUTS!$C$34*INPUTS!$C$39) -> 63 | G67: =IF(B67="","",D67) -> 16 | H67: =IF(B67="","",F67*G67) -> 1008 | I67: =IF(B67="","",E67-H67) -> 552 | J67: =IF(OR(B67="",E67=0),"",I67/E67) -> 0.35384615
B68: TOTALS | D68: =SUM(D47:D67) -> 224 | E68: =SUM(E47:E67) -> 20120 | G68: =SUM(G47:G67) -> 224 | H68: =SUM(H47:H67) -> 12336 | I68: =SUM(I47:I67) -> 7784 | J68: =IF(E68=0,"",I68/E68) -> 0.38687873
B70: STAFF OVERHEAD
B71: ITEM | C71: STAFF HOURS | D71: RATE / HR | E71: OVERHEAD COST
B72: Pre-planning staff hours | C72: =D43 -> 568 | D72: =INPUTS!$C$48 -> 0.61 | E72: =C72*D72 -> 346.48
B73: Onsite staff hours (incl. overtime) | C73: =D68 -> 224 | D73: =INPUTS!$C$48 -> 0.61 | E73: =C73*D73 -> 136.64
B74: TOTAL STAFF OVERHEAD | C74: =SUM(C72:C73) -> 792 | E74: =SUM(E72:E73) -> 483.12
B76: Overhead is a CTC cost — not billed, so it comes out of margin. The admin fee is charged on top of the client subtotal.

Sheet INPUTS
B1: CTC CONFERENCE P&L BUILDER — INPUTS
B2: Type in the yellow cells only. Choose the scope of work on the SCOPE tab. The P&L tab is all formulas — nothing to fill in there.
B4: 1. EVENT PROFILE
B5: Event / Client Name | C5: New Conference 2027
B6: Event Dates (display text) | C6: April 6-8, 2027
B7: Location | C7: Los Angeles, CA
B9: 2. EVENT SIZE
B10: Attendees | C10: 500 | D10: Main driver of the Event Scale Index below
B11: Exhibitors | C11: 60 | D11: Exhibit Management bills at 1 hour per exhibitor
B12: Sponsors | C12: 20 | D12: Sponsor Management bills at 1 hour per sponsor
B13: Speakers | C13: 15 | D13: Speaker Management bills at 1 hour per speaker, split prep / onsite
B14: Third-Party Vendors to Source | C14: 5 | D14: Third Party Vendors bills at 5 hours per vendor sourced
B15: Site Visits | C15: 1 | D15: Site Visits bills at 10 hours each (travel, walk-through, write-up)
B17: 3. SCHEDULE
B18: Event Days | C18: 3
B19: Set-Up / Load-In Days | C19: 1
B20: Travel Days | C20: 0
B21: TOTAL ONSITE DAYS | C21: =C18+C19+C20 -> 4
B22: Months of Pre-Planning | C22: 9 | D22: Months from contract signature to day 1 of the event
B23: Planning Weeks | C23: =ROUND(C22*4.33,0) -> 39 | D23: Weekly meetings, the project management system and approvals key off this
B24: EVENT SCALE INDEX | C24: =ROUND((MAX(1,C10)/250)^(1/3)*(MAX(1,C22)/6)^(1/2)*(MAX(1,C18)/3)^(1/4),2) -> 1.54 | D24: Calculated, not typed. 1.00 = a 250-person, 3-day event with 6 months of planning. Doubling attendance moves it about 26%, not 100%.
B26: 4. STAFFING (headcount)
B27: ONSITE — Managers | C27: 3 | D27: Onsite staff are costed PER PERSON — one line each on the P&L
B28: ONSITE — Coordinators | C28: 2
B29: PRE-PLANNING — Managers | C29: 1 | D29: Pre-planning is costed BY CATEGORY. Headcount sets the weekly meeting rate and the workload check on the P&L.
B30: PRE-PLANNING — Coordinators | C30: 1
B32: 5. RATES
B33: Manager — OUR COST / hr | C33: 60 | D33: Applies to every manager hour, pre-planning and onsite
B34: Coordinator — OUR COST / hr | C34: 42 | D34: Applies to every coordinator hour, pre-planning and onsite
B35: Manager — CLIENT RATE / hr (pre-planning) | C35: 90
B36: Coordinator — CLIENT RATE / hr (pre-planning) | C36: 65
B37: Manager — CLIENT RATE / hr (onsite) | C37: 100
B38: Coordinator — CLIENT RATE / hr (onsite) | C38: 65
B39: Overtime Multiplier | C39: 1.5 | D39: Coordinator overtime is billed and costed at 1.5x
B41: 6. ONSITE HOURS PER DAY
B42: Manager hours per onsite day | C42: 12 | D42: Applied to event days + set-up days
B43: Coordinator REGULAR hours per onsite day | C43: 8 | D43: Coordinators run 8 regular + 2 overtime on a normal show day
B44: Coordinator OVERTIME hours per onsite day | C44: 2
B45: Hours per travel day | C45: 8
B47: 7. OVERHEAD, FEES & DISCOUNTS
B48: Staff Overhead per hour | C48: 0.61 | D48: Charged against every CTC staff hour. A cost to us — not billed.
B49: Admin Fee % | C49: 0.02 | D49: 2% of the client subtotal, added to the client price. No cost against it.
B50: Multi-Year Discount % | C50: 0.05 | D50: The '5% off additional years' line, off unless switched on below.
B51: Apply Multi-Year Discount? | C51: No
B53: 8. ONSITE ROLE TITLES
B54: ONSITE MANAGERS | D54: Only the first N lines are used, where N is the headcount in section 4. Titles are labels only — rates come from section 5.
B55: Manager 1 | C55: Project Manager
B56: Manager 2 | C56: Event Manager
B57: Manager 3 | C57: Executive Producer
B58: Manager 4 | C58: Registration Manager
B59: Manager 5 | C59: Housing / Expo Manager
B60: Manager 6 | C60: Production Manager
B61: Manager 7 | C61: Manager 7
B62: Manager 8 | C62: Manager 8
B63: Manager 9 | C63: Manager 9
B64: Manager 10 | C64: Manager 10
B65: ONSITE COORDINATORS
B66: Coordinator 1 | C66: Event Coordinator
B67: Coordinator 2 | C67: Registration Coordinator
B68: Coordinator 3 | C68: Office Manager
B69: Coordinator 4 | C69: Production Assistant
B70: Coordinator 5 | C70: Exhibit Coordinator
B71: Coordinator 6 | C71: Housing Coordinator
B72: Coordinator 7 | C72: Coordinator 7
B73: Coordinator 8 | C73: Coordinator 8
B74: Coordinator 9 | C74: Coordinator 9
B75: Coordinator 10 | C75: Coordinator 10

Sheet SCOPE
A1: SCOPE OF WORK — matches the 2026 Master Proposal Template
B2: Set INCLUDE? on every line. Hours calculate from the INPUTS tab; type a number into OVERRIDE HOURS to force a line. The P&L rolls these up to the top-level headings.
A3: # | B3: SCOPE OF WORK ITEM | C3: TOP-LEVEL HEADING | D3: STAFF | E3: INCLUDE? | F3: HOW THE HOURS ARE CALCULATED | G3: CALC. HOURS | H3: OVERRIDE HOURS | I3: HOURS USED | J3: CLIENT RATE | K3: OUR RATE | L3: CLIENT COST | M3: OUR COST | P3: TOP-LEVEL HEADING | Q3: HOURS | R3: CLIENT COST | S3: OUR COST | T3: SEQ | U3: STAFF
A4: 1 | B4: PLANNING, TIMELINE & COMMUNICATIONS: Project Management System (ClickUp & Google Drive) | C4: PLANNING, TIMELINE & COMMUNICATIONS | D4: Coordinator | E4: Yes | F4: 1 hr per planning week | G4: =ROUND(1*INPUTS!$C$23,0) -> 39 | I4: =IF(ISNUMBER(H4),H4,G4) -> 39 | J4: =IF(D4="Manager",INPUTS!$C$35,IF(D4="Coordinator",INPUTS!$C$36,INPUTS!$C$29*INPUTS!$C$35+INPUTS!$C$30*INPUTS!$C$36)) -> 65 | K4: =IF(D4="Manager",INPUTS!$C$33,IF(D4="Coordinator",INPUTS!$C$34,INPUTS!$C$29*INPUTS!$C$33+INPUTS!$C$30*INPUTS!$C$34)) -> 42 | L4: =IF(E4="Yes",I4*J4,0) -> 2535 | M4: =IF(E4="Yes",I4*K4,0) -> 1638 | P4: PLANNING, TIMELINE & COMMUNICATIONS | Q4: =SUMIFS($I$4:$I$59,$C$4:$C$59,$P4,$E$4:$E$59,"Yes") -> 125 | R4: =SUMIF($C$4:$C$59,$P4,$L$4:$L$59) -> 12810 | S4: =SUMIF($C$4:$C$59,$P4,$M$4:$M$59) -> 8436 | T4: =IF(Q4>0,COUNTIF($Q$4:Q4,">0"),"") -> 1 | U4: =IF(Q4=0,"",IF(SUMIFS($I$4:$I$59,$C$4:$C$59,$P4,$E$4:$E$59,"Yes",$D$4:$D$59,"Manager")=Q4,"PM",IF(SUMIFS($I$4:$I$59,$C$4:$C$59,$P4,$E$4:$E$59,"Yes",$D$4:$D$59,"Coordinator")=Q4,"EC","PM/EC"))) -> PM/EC
A5: 2 | B5: PLANNING, TIMELINE & COMMUNICATIONS: Meetings, Minutes & Agendas | C5: PLANNING, TIMELINE & COMMUNICATIONS | D5: Team | E5: Yes | F5: 1 hr per planning week, whole team | G5: =ROUND(1*INPUTS!$C$23,0) -> 39 | I5: =IF(ISNUMBER(H5),H5,G5) -> 39 | J5: =IF(D5="Manager",INPUTS!$C$35,IF(D5="Coordinator",INPUTS!$C$36,INPUTS!$C$29*INPUTS!$C$35+INPUTS!$C$30*INPUTS!$C$36)) -> 155 | K5: =IF(D5="Manager",INPUTS!$C$33,IF(D5="Coordinator",INPUTS!$C$34,INPUTS!$C$29*INPUTS!$C$33+INPUTS!$C$30*INPUTS!$C$34)) -> 102 | L5: =IF(E5="Yes",I5*J5,0) -> 6045 | M5: =IF(E5="Yes",I5*K5,0) -> 3978 | P5: VENUE SOURCING | Q5: =SUMIFS($I$4:$I$59,$C$4:$C$59,$P5,$E$4:$E$59,"Yes") -> 0 | R5: =SUMIF($C$4:$C$59,$P5,$L$4:$L$59) -> 0 | S5: =SUMIF($C$4:$C$59,$P5,$M$4:$M$59) -> 0 | T5: =IF(Q5>0,COUNTIF($Q$4:Q5,">0"),"") | U5: =IF(Q5=0,"",IF(SUMIFS($I$4:$I$59,$C$4:$C$59,$P5,$E$4:$E$59,"Yes",$D$4:$D$59,"Manager")=Q5,"PM",IF(SUMIFS($I$4:$I$59,$C$4:$C$59,$P5,$E$4:$E$59,"Yes",$D$4:$D$59,"Coordinator")=Q5,"EC","PM/EC")))
A6: 3 | B6: PLANNING, TIMELINE & COMMUNICATIONS: Roles & Responsibilities | C6: PLANNING, TIMELINE & COMMUNICATIONS | D6: Manager | E6: Yes | F6: 5 x scale index | G6: =ROUND(5*INPUTS!$C$24,0) -> 8 | I6: =IF(ISNUMBER(H6),H6,G6) -> 8 | J6: =IF(D6="Manager",INPUTS!$C$35,IF(D6="Coordinator",INPUTS!$C$36,INPUTS!$C$29*INPUTS!$C$35+INPUTS!$C$30*INPUTS!$C$36)) -> 90 | K6: =IF(D6="Manager",INPUTS!$C$33,IF(D6="Coordinator",INPUTS!$C$34,INPUTS!$C$29*INPUTS!$C$33+INPUTS!$C$30*INPUTS!$C$34)) -> 60 | L6: =IF(E6="Yes",I6*J6,0) -> 720 | M6: =IF(E6="Yes",I6*K6,0) -> 480 | P6: VENUE MANAGEMENT | Q6: =SUMIFS($I$4:$I$59,$C$4:$C$59,$P6,$E$4:$E$59,"Yes") -> 40 | R6: =SUMIF($C$4:$C$59,$P6,$L$4:$L$59) -> 3600 | S6: =SUMIF($C$4:$C$59,$P6,$M$4:$M$59) -> 2400 | T6: =IF(Q6>0,COUNTIF($Q$4:Q6,">0"),"") -> 2 | U6: =IF(Q6=0,"",IF(SUMIFS($I$4:$I$59,$C$4:$C$59,$P6,$E$4:$E$59,"Yes",$D$4:$D$59,"Manager")=Q6,"PM",IF(SUMIFS($I$4:$I$59,$C$4:$C$59,$P6,$E$4:$E$59,"Yes",$D$4:$D$59,"Coordinator")=Q6,"EC","PM/EC"))) -> PM
A7: 4 | B7: PLANNING, TIMELINE & COMMUNICATIONS: Communication & Approvals | C7: PLANNING, TIMELINE & COMMUNICATIONS | D7: Manager | E7: Yes | F7: 1 hr per planning week | G7: =ROUND(1*INPUTS!$C$23,0) -> 39 | I7: =IF(ISNUMBER(H7),H7,G7) -> 39 | J7: =IF(D7="Manager",INPUTS!$C$35,IF(D7="Coordinator",INPUTS!$C$36,INPUTS!$C$29*INPUTS!$C$35+INPUTS!$C$30*INPUTS!$C$36)) -> 90 | K7: =IF(D7="Manager",INPUTS!$C$33,IF(D7="Coordinator",INPUTS!$C$34,INPUTS!$C$29*INPUTS!$C$33+INPUTS!$C$30*INPUTS!$C$34)) -> 60 | L7: =IF(E7="Yes",I7*J7,0) -> 3510 | M7: =IF(E7="Yes",I7*K7,0) -> 2340 | P7: EVENT BRANDING | Q7: =SUMIFS($I$4:$I$59,$C$4:$C$59,$P7,$E$4:$E$59,"Yes") -> 45 | R7: =SUMIF($C$4:$C$59,$P7,$L$4:$L$59) -> 4050 | S7: =SUMIF($C$4:$C$59,$P7,$M$4:$M$59) -> 2700 | T7: =IF(Q7>0,COUNTIF($Q$4:Q7,">0"),"") -> 3 | U7: =IF(Q7=0,"",IF(SUMIFS($I$4:$I$59,$C$4:$C$59,$P7,$E$4:$E$59,"Yes",$D$4:$D$59,"Manager")=Q7,"PM",IF(SUMIFS($I$4:$I$59,$C$4:$C$59,$P7,$E$4:$E$59,"Yes",$D$4:$D$59,"Coordinator")=Q7,"EC","PM/EC"))) -> PM
A8: 5 | B8: VENUE SOURCING: Request for Proposal | C8: VENUE SOURCING | D8: Manager | E8: No | F8: 6 x scale index | G8: =ROUND(6*INPUTS!$C$24,0) -> 9 | I8: =IF(ISNUMBER(H8),H8,G8) -> 9 | J8: =IF(D8="Manager",INPUTS!$C$35,IF(D8="Coordinator",INPUTS!$C$36,INPUTS!$C$29*INPUTS!$C$35+INPUTS!$C$30*INPUTS!$C$36)) -> 90 | K8: =IF(D8="Manager",INPUTS!$C$33,IF(D8="Coordinator",INPUTS!$C$34,INPUTS!$C$29*INPUTS!$C$33+INPUTS!$C$30*INPUTS!$C$34)) -> 60 | L8: =IF(E8="Yes",I8*J8,0) -> 0 | M8: =IF(E8="Yes",I8*K8,0) -> 0 | P8: FOOD & BEVERAGE | Q8: =SUMIFS($I$4:$I$59,$C$4:$C$59,$P8,$E$4:$E$59,"Yes") -> 34 | R8: =SUMIF($C$4:$C$59,$P8,$L$4:$L$59) -> 3060 | S8: =SUMIF($C$4:$C$59,$P8,$M$4:$M$59) -> 2040 | T8: =IF(Q8>0,COUNTIF($Q$4:Q8,">0"),"") -> 4 | U8: =IF(Q8=0,"",IF(SUMIFS($I$4:$I$59,$C$4:$C$59,$P8,$E$4:$E$59,"Yes",$D$4:$D$59,"Manager")=Q8,"PM",IF(SUMIFS($I$4:$I$59,$C$4:$C$59,$P8,$E$4:$E$59,"Yes",$D$4:$D$59,"Coordinator")=Q8,"EC","PM/EC"))) -> PM
A9: 6 | B9: VENUE SOURCING: Venue/Hotel Analysis | C9: VENUE SOURCING | D9: Manager | E9: No | F9: 6 x scale index | G9: =ROUND(6*INPUTS!$C$24,0) -> 9 | I9: =IF(ISNUMBER(H9),H9,G9) -> 9 | J9: =IF(D9="Manager",INPUTS!$C$35,IF(D9="Coordinator",INPUTS!$C$36,INPUTS!$C$29*INPUTS!$C$35+INPUTS!$C$30*INPUTS!$C$36)) -> 90 | K9: =IF(D9="Manager",INPUTS!$C$33,IF(D9="Coordinator",INPUTS!$C$34,INPUTS!$C$29*INPUTS!$C$33+INPUTS!$C$30*INPUTS!$C$34)) -> 60 | L9: =IF(E9="Yes",I9*J9,0) -> 0 | M9: =IF(E9="Yes",I9*K9,0) -> 0 | P9: REGISTRATION | Q9: =SUMIFS($I$4:$I$59,$C$4:$C$59,$P9,$E$4:$E$59,"Yes") -> 82 | R9: =SUMIF($C$4:$C$59,$P9,$L$4:$L$59) -> 5330 | S9: =SUMIF($C$4:$C$59,$P9,$M$4:$M$59) -> 3444 | T9: =IF(Q9>0,COUNTIF($Q$4:Q9,">0"),"") -> 5 | U9: =IF(Q9=0,"",IF(SUMIFS($I$4:$I$59,$C$4:$C$59,$P9,$E$4:$E$59,"Yes",$D$4:$D$59,"Manager")=Q9,"PM",IF(SUMIFS($I$4:$I$59,$C$4:$C$59,$P9,$E$4:$E$59,"Yes",$D$4:$D$59,"Coordinator")=Q9,"EC","PM/EC"))) -> EC
A10: 7 | B10: VENUE SOURCING: Site Visits | C10: VENUE SOURCING | D10: Manager | E10: No | F10: 10 hrs per site visit | G10: =ROUND(10*INPUTS!$C$15,0) -> 10 | I10: =IF(ISNUMBER(H10),H10,G10) -> 10 | J10: =IF(D10="Manager",INPUTS!$C$35,IF(D10="Coordinator",INPUTS!$C$36,INPUTS!$C$29*INPUTS!$C$35+INPUTS!$C$30*INPUTS!$C$36)) -> 90 | K10: =IF(D10="Manager",INPUTS!$C$33,IF(D10="Coordinator",INPUTS!$C$34,INPUTS!$C$29*INPUTS!$C$33+INPUTS!$C$30*INPUTS!$C$34)) -> 60 | L10: =IF(E10="Yes",I10*J10,0) -> 0 | M10: =IF(E10="Yes",I10*K10,0) -> 0 | P10: SWAG BAG | Q10: =SUMIFS($I$4:$I$59,$C$4:$C$59,$P10,$E$4:$E$59,"Yes") -> 0 | R10: =SUMIF($C$4:$C$59,$P10,$L$4:$L$59) -> 0 | S10: =SUMIF($C$4:$C$59,$P10,$M$4:$M$59) -> 0 | T10: =IF(Q10>0,COUNTIF($Q$4:Q10,">0"),"") | U10: =IF(Q10=0,"",IF(SUMIFS($I$4:$I$59,$C$4:$C$59,$P10,$E$4:$E$59,"Yes",$D$4:$D$59,"Manager")=Q10,"PM",IF(SUMIFS($I$4:$I$59,$C$4:$C$59,$P10,$E$4:$E$59,"Yes",$D$4:$D$59,"Coordinator")=Q10,"EC","PM/EC")))
A11: 8 | B11: VENUE SOURCING: Contract Negotiations | C11: VENUE SOURCING | D11: Manager | E11: No | F11: 5 x scale index | G11: =ROUND(5*INPUTS!$C$24,0) -> 8 | I11: =IF(ISNUMBER(H11),H11,G11) -> 8 | J11: =IF(D11="Manager",INPUTS!$C$35,IF(D11="Coordinator",INPUTS!$C$36,INPUTS!$C$29*INPUTS!$C$35+INPUTS!$C$30*INPUTS!$C$36)) -> 90 | K11: =IF(D11="Manager",INPUTS!$C$33,IF(D11="Coordinator",INPUTS!$C$34,INPUTS!$C$29*INPUTS!$C$33+INPUTS!$C$30*INPUTS!$C$34)) -> 60 | L11: =IF(E11="Yes",I11*J11,0) -> 0 | M11: =IF(E11="Yes",I11*K11,0) -> 0 | P11: HOUSING LOGISTICS | Q11: =SUMIFS($I$4:$I$59,$C$4:$C$59,$P11,$E$4:$E$59,"Yes") -> 0 | R11: =SUMIF($C$4:$C$59,$P11,$L$4:$L$59) -> 0 | S11: =SUMIF($C$4:$C$59,$P11,$M$4:$M$59) -> 0 | T11: =IF(Q11>0,COUNTIF($Q$4:Q11,">0"),"") | U11: =IF(Q11=0,"",IF(SUMIFS($I$4:$I$59,$C$4:$C$59,$P11,$E$4:$E$59,"Yes",$D$4:$D$59,"Manager")=Q11,"PM",IF(SUMIFS($I$4:$I$59,$C$4:$C$59,$P11,$E$4:$E$59,"Yes",$D$4:$D$59,"Coordinator")=Q11,"EC","PM/EC")))
A12: 9 | B12: VENUE MANAGEMENT: Venue Logistics | C12: VENUE MANAGEMENT | D12: Manager | E12: Yes | F12: 16 x scale index | G12: =ROUND(16*INPUTS!$C$24,0) -> 25 | I12: =IF(ISNUMBER(H12),H12,G12) -> 25 | J12: =IF(D12="Manager",INPUTS!$C$35,IF(D12="Coordinator",INPUTS!$C$36,INPUTS!$C$29*INPUTS!$C$35+INPUTS!$C$30*INPUTS!$C$36)) -> 90 | K12: =IF(D12="Manager",INPUTS!$C$33,IF(D12="Coordinator",INPUTS!$C$34,INPUTS!$C$29*INPUTS!$C$33+INPUTS!$C$30*INPUTS!$C$34)) -> 60 | L12: =IF(E12="Yes",I12*J12,0) -> 2250 | M12: =IF(E12="Yes",I12*K12,0) -> 1500 | P12: THIRD PARTY VENDORS | Q12: =SUMIFS($I$4:$I$59,$C$4:$C$59,$P12,$E$4:$E$59,"Yes") -> 40 | R12: =SUMIF($C$4:$C$59,$P12,$L$4:$L$59) -> 2600 | S12: =SUMIF($C$4:$C$59,$P12,$M$4:$M$59) -> 1680 | T12: =IF(Q12>0,COUNTIF($Q$4:Q12,">0"),"") -> 6 | U12: =IF(Q12=0,"",IF(SUMIFS($I$4:$I$59,$C$4:$C$59,$P12,$E$4:$E$59,"Yes",$D$4:$D$59,"Manager")=Q12,"PM",IF(SUMIFS($I$4:$I$59,$C$4:$C$59,$P12,$E$4:$E$59,"Yes",$D$4:$D$59,"Coordinator")=Q12,"EC","PM/EC"))) -> EC
A13: 10 | B13: VENUE MANAGEMENT: Meeting Space | C13: VENUE MANAGEMENT | D13: Manager | E13: Yes | F13: 10 x scale index | G13: =ROUND(10*INPUTS!$C$24,0) -> 15 | I13: =IF(ISNUMBER(H13),H13,G13) -> 15 | J13: =IF(D13="Manager",INPUTS!$C$35,IF(D13="Coordinator",INPUTS!$C$36,INPUTS!$C$29*INPUTS!$C$35+INPUTS!$C$30*INPUTS!$C$36)) -> 90 | K13: =IF(D13="Manager",INPUTS!$C$33,IF(D13="Coordinator",INPUTS!$C$34,INPUTS!$C$29*INPUTS!$C$33+INPUTS!$C$30*INPUTS!$C$34)) -> 60 | L13: =IF(E13="Yes",I13*J13,0) -> 1350 | M13: =IF(E13="Yes",I13*K13,0) -> 900 | P13: STAFF MANAGEMENT | Q13: =SUMIFS($I$4:$I$59,$C$4:$C$59,$P13,$E$4:$E$59,"Yes") -> 14 | R13: =SUMIF($C$4:$C$59,$P13,$L$4:$L$59) -> 1260 | S13: =SUMIF($C$4:$C$59,$P13,$M$4:$M$59) -> 840 | T13: =IF(Q13>0,COUNTIF($Q$4:Q13,">0"),"") -> 7 | U13: =IF(Q13=0,"",IF(SUMIFS($I$4:$I$59,$C$4:$C$59,$P13,$E$4:$E$59,"Yes",$D$4:$D$59,"Manager")=Q13,"PM",IF(SUMIFS($I$4:$I$59,$C$4:$C$59,$P13,$E$4:$E$59,"Yes",$D$4:$D$59,"Coordinator")=Q13,"EC","PM/EC"))) -> PM
A14: 11 | B14: EVENT BRANDING: Attendee Experience | C14: EVENT BRANDING | D14: Manager | E14: Yes | F14: 7 x scale index | G14: =ROUND(7*INPUTS!$C$24,0) -> 11 | I14: =IF(ISNUMBER(H14),H14,G14) -> 11 | J14: =IF(D14="Manager",INPUTS!$C$35,IF(D14="Coordinator",INPUTS!$C$36,INPUTS!$C$29*INPUTS!$C$35+INPUTS!$C$30*INPUTS!$C$36)) -> 90 | K14: =IF(D14="Manager",INPUTS!$C$33,IF(D14="Coordinator",INPUTS!$C$34,INPUTS!$C$29*INPUTS!$C$33+INPUTS!$C$30*INPUTS!$C$34)) -> 60 | L14: =IF(E14="Yes",I14*J14,0) -> 990 | M14: =IF(E14="Yes",I14*K14,0) -> 660 | P14: VIP & PRESS LOGISTICS | Q14: =SUMIFS($I$4:$I$59,$C$4:$C$59,$P14,$E$4:$E$59,"Yes") -> 0 | R14: =SUMIF($C$4:$C$59,$P14,$L$4:$L$59) -> 0 | S14: =SUMIF($C$4:$C$59,$P14,$M$4:$M$59) -> 0 | T14: =IF(Q14>0,COUNTIF($Q$4:Q14,">0"),"") | U14: =IF(Q14=0,"",IF(SUMIFS($I$4:$I$59,$C$4:$C$59,$P14,$E$4:$E$59,"Yes",$D$4:$D$59,"Manager")=Q14,"PM",IF(SUMIFS($I$4:$I$59,$C$4:$C$59,$P14,$E$4:$E$59,"Yes",$D$4:$D$59,"Coordinator")=Q14,"EC","PM/EC")))
A15: 12 | B15: EVENT BRANDING: Signage | C15: EVENT BRANDING | D15: Manager | E15: Yes | F15: 14 x scale index | G15: =ROUND(14*INPUTS!$C$24,0) -> 22 | I15: =IF(ISNUMBER(H15),H15,G15) -> 22 | J15: =IF(D15="Manager",INPUTS!$C$35,IF(D15="Coordinator",INPUTS!$C$36,INPUTS!$C$29*INPUTS!$C$35+INPUTS!$C$30*INPUTS!$C$36)) -> 90 | K15: =IF(D15="Manager",INPUTS!$C$33,IF(D15="Coordinator",INPUTS!$C$34,INPUTS!$C$29*INPUTS!$C$33+INPUTS!$C$30*INPUTS!$C$34)) -> 60 | L15: =IF(E15="Yes",I15*J15,0) -> 1980 | M15: =IF(E15="Yes",I15*K15,0) -> 1320 | P15: SPONSORSHIPS | Q15: =SUMIFS($I$4:$I$59,$C$4:$C$59,$P15,$E$4:$E$59,"Yes") -> 32 | R15: =SUMIF($C$4:$C$59,$P15,$L$4:$L$59) -> 2080 | S15: =SUMIF($C$4:$C$59,$P15,$M$4:$M$59) -> 1344 | T15: =IF(Q15>0,COUNTIF($Q$4:Q15,">0"),"") -> 8 | U15: =IF(Q15=0,"",IF(SUMIFS($I$4:$I$59,$C$4:$C$59,$P15,$E$4:$E$59,"Yes",$D$4:$D$59,"Manager")=Q15,"PM",IF(SUMIFS($I$4:$I$59,$C$4:$C$59,$P15,$E$4:$E$59,"Yes",$D$4:$D$59,"Coordinator")=Q15,"EC","PM/EC"))) -> EC
A16: 13 | B16: EVENT BRANDING: Décor | C16: EVENT BRANDING | D16: Manager | E16: Yes | F16: 8 x scale index | G16: =ROUND(8*INPUTS!$C$24,0) -> 12 | I16: =IF(ISNUMBER(H16),H16,G16) -> 12 | J16: =IF(D16="Manager",INPUTS!$C$35,IF(D16="Coordinator",INPUTS!$C$36,INPUTS!$C$29*INPUTS!$C$35+INPUTS!$C$30*INPUTS!$C$36)) -> 90 | K16: =IF(D16="Manager",INPUTS!$C$33,IF(D16="Coordinator",INPUTS!$C$34,INPUTS!$C$29*INPUTS!$C$33+INPUTS!$C$30*INPUTS!$C$34)) -> 60 | L16: =IF(E16="Yes",I16*J16,0) -> 1080 | M16: =IF(E16="Yes",I16*K16,0) -> 720 | P16: SPEAKER MANAGEMENT | Q16: =SUMIFS($I$4:$I$59,$C$4:$C$59,$P16,$E$4:$E$59,"Yes") -> 0 | R16: =SUMIF($C$4:$C$59,$P16,$L$4:$L$59) -> 0 | S16: =SUMIF($C$4:$C$59,$P16,$M$4:$M$59) -> 0 | T16: =IF(Q16>0,COUNTIF($Q$4:Q16,">0"),"") | U16: =IF(Q16=0,"",IF(SUMIFS($I$4:$I$59,$C$4:$C$59,$P16,$E$4:$E$59,"Yes",$D$4:$D$59,"Manager")=Q16,"PM",IF(SUMIFS($I$4:$I$59,$C$4:$C$59,$P16,$E$4:$E$59,"Yes",$D$4:$D$59,"Coordinator")=Q16,"EC","PM/EC")))
A17: 14 | B17: EVENT BRANDING: Graphic Design (add-on) | C17: EVENT BRANDING | D17: Manager | E17: No | F17: 26 x scale index | G17: =ROUND(26*INPUTS!$C$24,0) -> 40 | I17: =IF(ISNUMBER(H17),H17,G17) -> 40 | J17: =IF(D17="Manager",INPUTS!$C$35,IF(D17="Coordinator",INPUTS!$C$36,INPUTS!$C$29*INPUTS!$C$35+INPUTS!$C$30*INPUTS!$C$36)) -> 90 | K17: =IF(D17="Manager",INPUTS!$C$33,IF(D17="Coordinator",INPUTS!$C$34,INPUTS!$C$29*INPUTS!$C$33+INPUTS!$C$30*INPUTS!$C$34)) -> 60 | L17: =IF(E17="Yes",I17*J17,0) -> 0 | M17: =IF(E17="Yes",I17*K17,0) -> 0 | P17: PROGRAMMING | Q17: =SUMIFS($I$4:$I$59,$C$4:$C$59,$P17,$E$4:$E$59,"Yes") -> 63 | R17: =SUMIF($C$4:$C$59,$P17,$L$4:$L$59) -> 5670 | S17: =SUMIF($C$4:$C$59,$P17,$M$4:$M$59) -> 3780 | T17: =IF(Q17>0,COUNTIF($Q$4:Q17,">0"),"") -> 9 | U17: =IF(Q17=0,"",IF(SUMIFS($I$4:$I$59,$C$4:$C$59,$P17,$E$4:$E$59,"Yes",$D$4:$D$59,"Manager")=Q17,"PM",IF(SUMIFS($I$4:$I$59,$C$4:$C$59,$P17,$E$4:$E$59,"Yes",$D$4:$D$59,"Coordinator")=Q17,"EC","PM/EC"))) -> PM
A18: 15 | B18: FOOD & BEVERAGE: Food & Beverage Management | C18: FOOD & BEVERAGE | D18: Manager | E18: Yes | F18: 22 x scale index | G18: =ROUND(22*INPUTS!$C$24,0) -> 34 | I18: =IF(ISNUMBER(H18),H18,G18) -> 34 | J18: =IF(D18="Manager",INPUTS!$C$35,IF(D18="Coordinator",INPUTS!$C$36,INPUTS!$C$29*INPUTS!$C$35+INPUTS!$C$30*INPUTS!$C$36)) -> 90 | K18: =IF(D18="Manager",INPUTS!$C$33,IF(D18="Coordinator",INPUTS!$C$34,INPUTS!$C$29*INPUTS!$C$33+INPUTS!$C$30*INPUTS!$C$34)) -> 60 | L18: =IF(E18="Yes",I18*J18,0) -> 3060 | M18: =IF(E18="Yes",I18*K18,0) -> 2040 | P18: RECEPTION PLANNING | Q18: =SUMIFS($I$4:$I$59,$C$4:$C$59,$P18,$E$4:$E$59,"Yes") -> 0 | R18: =SUMIF($C$4:$C$59,$P18,$L$4:$L$59) -> 0 | S18: =SUMIF($C$4:$C$59,$P18,$M$4:$M$59) -> 0 | T18: =IF(Q18>0,COUNTIF($Q$4:Q18,">0"),"") | U18: =IF(Q18=0,"",IF(SUMIFS($I$4:$I$59,$C$4:$C$59,$P18,$E$4:$E$59,"Yes",$D$4:$D$59,"Manager")=Q18,"PM",IF(SUMIFS($I$4:$I$59,$C$4:$C$59,$P18,$E$4:$E$59,"Yes",$D$4:$D$59,"Coordinator")=Q18,"EC","PM/EC")))
A19: 16 | B19: REGISTRATION: Online Registration / Build-Out | C19: REGISTRATION | D19: Coordinator | E19: Yes | F19: 35 x scale index | G19: =ROUND(35*INPUTS!$C$24,0) -> 54 | I19: =IF(ISNUMBER(H19),H19,G19) -> 54 | J19: =IF(D19="Manager",INPUTS!$C$35,IF(D19="Coordinator",INPUTS!$C$36,INPUTS!$C$29*INPUTS!$C$35+INPUTS!$C$30*INPUTS!$C$36)) -> 65 | K19: =IF(D19="Manager",INPUTS!$C$33,IF(D19="Coordinator",INPUTS!$C$34,INPUTS!$C$29*INPUTS!$C$33+INPUTS!$C$30*INPUTS!$C$34)) -> 42 | L19: =IF(E19="Yes",I19*J19,0) -> 3510 | M19: =IF(E19="Yes",I19*K19,0) -> 2268 | P19: FINANCIAL MANAGEMENT | Q19: =SUMIFS($I$4:$I$59,$C$4:$C$59,$P19,$E$4:$E$59,"Yes") -> 18 | R19: =SUMIF($C$4:$C$59,$P19,$L$4:$L$59) -> 1620 | S19: =SUMIF($C$4:$C$59,$P19,$M$4:$M$59) -> 1080 | T19: =IF(Q19>0,COUNTIF($Q$4:Q19,">0"),"") -> 10 | U19: =IF(Q19=0,"",IF(SUMIFS($I$4:$I$59,$C$4:$C$59,$P19,$E$4:$E$59,"Yes",$D$4:$D$59,"Manager")=Q19,"PM",IF(SUMIFS($I$4:$I$59,$C$4:$C$59,$P19,$E$4:$E$59,"Yes",$D$4:$D$59,"Coordinator")=Q19,"EC","PM/EC"))) -> PM
A20: 17 | B20: REGISTRATION: Onsite Registration | C20: REGISTRATION | D20: Coordinator | E20: Yes | F20: 18 x scale index | G20: =ROUND(18*INPUTS!$C$24,0) -> 28 | I20: =IF(ISNUMBER(H20),H20,G20) -> 28 | J20: =IF(D20="Manager",INPUTS!$C$35,IF(D20="Coordinator",INPUTS!$C$36,INPUTS!$C$29*INPUTS!$C$35+INPUTS!$C$30*INPUTS!$C$36)) -> 65 | K20: =IF(D20="Manager",INPUTS!$C$33,IF(D20="Coordinator",INPUTS!$C$34,INPUTS!$C$29*INPUTS!$C$33+INPUTS!$C$30*INPUTS!$C$34)) -> 42 | L20: =IF(E20="Yes",I20*J20,0) -> 1820 | M20: =IF(E20="Yes",I20*K20,0) -> 1176 | P20: EVENT MARKETING | Q20: =SUMIFS($I$4:$I$59,$C$4:$C$59,$P20,$E$4:$E$59,"Yes") -> 0 | R20: =SUMIF($C$4:$C$59,$P20,$L$4:$L$59) -> 0 | S20: =SUMIF($C$4:$C$59,$P20,$M$4:$M$59) -> 0 | T20: =IF(Q20>0,COUNTIF($Q$4:Q20,">0"),"") | U20: =IF(Q20=0,"",IF(SUMIFS($I$4:$I$59,$C$4:$C$59,$P20,$E$4:$E$59,"Yes",$D$4:$D$59,"Manager")=Q20,"PM",IF(SUMIFS($I$4:$I$59,$C$4:$C$59,$P20,$E$4:$E$59,"Yes",$D$4:$D$59,"Coordinator")=Q20,"EC","PM/EC")))
A21: 18 | B21: REGISTRATION: Mobile App | C21: REGISTRATION | D21: Coordinator | E21: No | F21: 25 x scale index | G21: =ROUND(25*INPUTS!$C$24,0) -> 39 | I21: =IF(ISNUMBER(H21),H21,G21) -> 39 | J21: =IF(D21="Manager",INPUTS!$C$35,IF(D21="Coordinator",INPUTS!$C$36,INPUTS!$C$29*INPUTS!$C$35+INPUTS!$C$30*INPUTS!$C$36)) -> 65 | K21: =IF(D21="Manager",INPUTS!$C$33,IF(D21="Coordinator",INPUTS!$C$34,INPUTS!$C$29*INPUTS!$C$33+INPUTS!$C$30*INPUTS!$C$34)) -> 42 | L21: =IF(E21="Yes",I21*J21,0) -> 0 | M21: =IF(E21="Yes",I21*K21,0) -> 0 | P21: EXHIBIT MANAGEMENT | Q21: =SUMIFS($I$4:$I$59,$C$4:$C$59,$P21,$E$4:$E$59,"Yes") -> 60 | R21: =SUMIF($C$4:$C$59,$P21,$L$4:$L$59) -> 5400 | S21: =SUMIF($C$4:$C$59,$P21,$M$4:$M$59) -> 3600 | T21: =IF(Q21>0,COUNTIF($Q$4:Q21,">0"),"") -> 11 | U21: =IF(Q21=0,"",IF(SUMIFS($I$4:$I$59,$C$4:$C$59,$P21,$E$4:$E$59,"Yes",$D$4:$D$59,"Manager")=Q21,"PM",IF(SUMIFS($I$4:$I$59,$C$4:$C$59,$P21,$E$4:$E$59,"Yes",$D$4:$D$59,"Coordinator")=Q21,"EC","PM/EC"))) -> PM
A22: 19 | B22: SWAG BAG: Swag Bag Sourcing, Assembly & Distribution | C22: SWAG BAG | D22: Coordinator | E22: No | F22: 20 x scale index | G22: =ROUND(20*INPUTS!$C$24,0) -> 31 | I22: =IF(ISNUMBER(H22),H22,G22) -> 31 | J22: =IF(D22="Manager",INPUTS!$C$35,IF(D22="Coordinator",INPUTS!$C$36,INPUTS!$C$29*INPUTS!$C$35+INPUTS!$C$30*INPUTS!$C$36)) -> 65 | K22: =IF(D22="Manager",INPUTS!$C$33,IF(D22="Coordinator",INPUTS!$C$34,INPUTS!$C$29*INPUTS!$C$33+INPUTS!$C$30*INPUTS!$C$34)) -> 42 | L22: =IF(E22="Yes",I22*J22,0) -> 0 | M22: =IF(E22="Yes",I22*K22,0) -> 0 | P22: POST-EVENT | Q22: =SUMIFS($I$4:$I$59,$C$4:$C$59,$P22,$E$4:$E$59,"Yes") -> 15 | R22: =SUMIF($C$4:$C$59,$P22,$L$4:$L$59) -> 1350 | S22: =SUMIF($C$4:$C$59,$P22,$M$4:$M$59) -> 900 | T22: =IF(Q22>0,COUNTIF($Q$4:Q22,">0"),"") -> 12 | U22: =IF(Q22=0,"",IF(SUMIFS($I$4:$I$59,$C$4:$C$59,$P22,$E$4:$E$59,"Yes",$D$4:$D$59,"Manager")=Q22,"PM",IF(SUMIFS($I$4:$I$59,$C$4:$C$59,$P22,$E$4:$E$59,"Yes",$D$4:$D$59,"Coordinator")=Q22,"EC","PM/EC"))) -> PM
A23: 20 | B23: HOUSING LOGISTICS: Room Blocks | C23: HOUSING LOGISTICS | D23: Coordinator | E23: No | F23: 8 x scale index | G23: =ROUND(8*INPUTS!$C$24,0) -> 12 | I23: =IF(ISNUMBER(H23),H23,G23) -> 12 | J23: =IF(D23="Manager",INPUTS!$C$35,IF(D23="Coordinator",INPUTS!$C$36,INPUTS!$C$29*INPUTS!$C$35+INPUTS!$C$30*INPUTS!$C$36)) -> 65 | K23: =IF(D23="Manager",INPUTS!$C$33,IF(D23="Coordinator",INPUTS!$C$34,INPUTS!$C$29*INPUTS!$C$33+INPUTS!$C$30*INPUTS!$C$34)) -> 42 | L23: =IF(E23="Yes",I23*J23,0) -> 0 | M23: =IF(E23="Yes",I23*K23,0) -> 0 | P23: TOURNAMENTS | Q23: =SUMIFS($I$4:$I$59,$C$4:$C$59,$P23,$E$4:$E$59,"Yes") -> 0 | R23: =SUMIF($C$4:$C$59,$P23,$L$4:$L$59) -> 0 | S23: =SUMIF($C$4:$C$59,$P23,$M$4:$M$59) -> 0 | T23: =IF(Q23>0,COUNTIF($Q$4:Q23,">0"),"") | U23: =IF(Q23=0,"",IF(SUMIFS($I$4:$I$59,$C$4:$C$59,$P23,$E$4:$E$59,"Yes",$D$4:$D$59,"Manager")=Q23,"PM",IF(SUMIFS($I$4:$I$59,$C$4:$C$59,$P23,$E$4:$E$59,"Yes",$D$4:$D$59,"Coordinator")=Q23,"EC","PM/EC")))
A24: 21 | B24: HOUSING LOGISTICS: Housing Reports | C24: HOUSING LOGISTICS | D24: Coordinator | E24: No | F24: 4 x scale index | G24: =ROUND(4*INPUTS!$C$24,0) -> 6 | I24: =IF(ISNUMBER(H24),H24,G24) -> 6 | J24: =IF(D24="Manager",INPUTS!$C$35,IF(D24="Coordinator",INPUTS!$C$36,INPUTS!$C$29*INPUTS!$C$35+INPUTS!$C$30*INPUTS!$C$36)) -> 65 | K24: =IF(D24="Manager",INPUTS!$C$33,IF(D24="Coordinator",INPUTS!$C$34,INPUTS!$C$29*INPUTS!$C$33+INPUTS!$C$30*INPUTS!$C$34)) -> 42 | L24: =IF(E24="Yes",I24*J24,0) -> 0 | M24: =IF(E24="Yes",I24*K24,0) -> 0
A25: 22 | B25: HOUSING LOGISTICS: Concession Management | C25: HOUSING LOGISTICS | D25: Coordinator | E25: No | F25: 3 x scale index | G25: =ROUND(3*INPUTS!$C$24,0) -> 5 | I25: =IF(ISNUMBER(H25),H25,G25) -> 5 | J25: =IF(D25="Manager",INPUTS!$C$35,IF(D25="Coordinator",INPUTS!$C$36,INPUTS!$C$29*INPUTS!$C$35+INPUTS!$C$30*INPUTS!$C$36)) -> 65 | K25: =IF(D25="Manager",INPUTS!$C$33,IF(D25="Coordinator",INPUTS!$C$34,INPUTS!$C$29*INPUTS!$C$33+INPUTS!$C$30*INPUTS!$C$34)) -> 42 | L25: =IF(E25="Yes",I25*J25,0) -> 0 | M25: =IF(E25="Yes",I25*K25,0) -> 0
A26: 23 | B26: HOUSING LOGISTICS: Attendee Liaison | C26: HOUSING LOGISTICS | D26: Coordinator | E26: No | F26: 5 x scale index | G26: =ROUND(5*INPUTS!$C$24,0) -> 8 | I26: =IF(ISNUMBER(H26),H26,G26) -> 8 | J26: =IF(D26="Manager",INPUTS!$C$35,IF(D26="Coordinator",INPUTS!$C$36,INPUTS!$C$29*INPUTS!$C$35+INPUTS!$C$30*INPUTS!$C$36)) -> 65 | K26: =IF(D26="Manager",INPUTS!$C$33,IF(D26="Coordinator",INPUTS!$C$34,INPUTS!$C$29*INPUTS!$C$33+INPUTS!$C$30*INPUTS!$C$34)) -> 42 | L26: =IF(E26="Yes",I26*J26,0) -> 0 | M26: =IF(E26="Yes",I26*K26,0) -> 0
A27: 24 | B27: HOUSING LOGISTICS: Overflow Hotel Sourcing | C27: HOUSING LOGISTICS | D27: Coordinator | E27: No | F27: 3 x scale index | G27: =ROUND(3*INPUTS!$C$24,0) -> 5 | I27: =IF(ISNUMBER(H27),H27,G27) -> 5 | J27: =IF(D27="Manager",INPUTS!$C$35,IF(D27="Coordinator",INPUTS!$C$36,INPUTS!$C$29*INPUTS!$C$35+INPUTS!$C$30*INPUTS!$C$36)) -> 65 | K27: =IF(D27="Manager",INPUTS!$C$33,IF(D27="Coordinator",INPUTS!$C$34,INPUTS!$C$29*INPUTS!$C$33+INPUTS!$C$30*INPUTS!$C$34)) -> 42 | L27: =IF(E27="Yes",I27*J27,0) -> 0 | M27: =IF(E27="Yes",I27*K27,0) -> 0
A28: 25 | B28: THIRD PARTY VENDORS: Vendors | C28: THIRD PARTY VENDORS | D28: Coordinator | E28: Yes | F28: 5 hrs per vendor sourced | G28: =ROUND(5*INPUTS!$C$14,0) -> 25 | I28: =IF(ISNUMBER(H28),H28,G28) -> 25 | J28: =IF(D28="Manager",INPUTS!$C$35,IF(D28="Coordinator",INPUTS!$C$36,INPUTS!$C$29*INPUTS!$C$35+INPUTS!$C$30*INPUTS!$C$36)) -> 65 | K28: =IF(D28="Manager",INPUTS!$C$33,IF(D28="Coordinator",INPUTS!$C$34,INPUTS!$C$29*INPUTS!$C$33+INPUTS!$C$30*INPUTS!$C$34)) -> 42 | L28: =IF(E28="Yes",I28*J28,0) -> 1625 | M28: =IF(E28="Yes",I28*K28,0) -> 1050
A29: 26 | B29: THIRD PARTY VENDORS: Photographer / Videographer | C29: THIRD PARTY VENDORS | D29: Coordinator | E29: Yes | F29: 10 x scale index | G29: =ROUND(10*INPUTS!$C$24,0) -> 15 | I29: =IF(ISNUMBER(H29),H29,G29) -> 15 | J29: =IF(D29="Manager",INPUTS!$C$35,IF(D29="Coordinator",INPUTS!$C$36,INPUTS!$C$29*INPUTS!$C$35+INPUTS!$C$30*INPUTS!$C$36)) -> 65 | K29: =IF(D29="Manager",INPUTS!$C$33,IF(D29="Coordinator",INPUTS!$C$34,INPUTS!$C$29*INPUTS!$C$33+INPUTS!$C$30*INPUTS!$C$34)) -> 42 | L29: =IF(E29="Yes",I29*J29,0) -> 975 | M29: =IF(E29="Yes",I29*K29,0) -> 630
A30: 27 | B30: STAFF MANAGEMENT: Temporary Staff | C30: STAFF MANAGEMENT | D30: Manager | E30: Yes | F30: 5 x scale index | G30: =ROUND(5*INPUTS!$C$24,0) -> 8 | I30: =IF(ISNUMBER(H30),H30,G30) -> 8 | J30: =IF(D30="Manager",INPUTS!$C$35,IF(D30="Coordinator",INPUTS!$C$36,INPUTS!$C$29*INPUTS!$C$35+INPUTS!$C$30*INPUTS!$C$36)) -> 90 | K30: =IF(D30="Manager",INPUTS!$C$33,IF(D30="Coordinator",INPUTS!$C$34,INPUTS!$C$29*INPUTS!$C$33+INPUTS!$C$30*INPUTS!$C$34)) -> 60 | L30: =IF(E30="Yes",I30*J30,0) -> 720 | M30: =IF(E30="Yes",I30*K30,0) -> 480
A31: 28 | B31: STAFF MANAGEMENT: Volunteers | C31: STAFF MANAGEMENT | D31: Manager | E31: Yes | F31: 4 x scale index | G31: =ROUND(4*INPUTS!$C$24,0) -> 6 | I31: =IF(ISNUMBER(H31),H31,G31) -> 6 | J31: =IF(D31="Manager",INPUTS!$C$35,IF(D31="Coordinator",INPUTS!$C$36,INPUTS!$C$29*INPUTS!$C$35+INPUTS!$C$30*INPUTS!$C$36)) -> 90 | K31: =IF(D31="Manager",INPUTS!$C$33,IF(D31="Coordinator",INPUTS!$C$34,INPUTS!$C$29*INPUTS!$C$33+INPUTS!$C$30*INPUTS!$C$34)) -> 60 | L31: =IF(E31="Yes",I31*J31,0) -> 540 | M31: =IF(E31="Yes",I31*K31,0) -> 360
A32: 29 | B32: VIP & PRESS LOGISTICS: VIPs | C32: VIP & PRESS LOGISTICS | D32: Coordinator | E32: No | F32: 12 x scale index | G32: =ROUND(12*INPUTS!$C$24,0) -> 18 | I32: =IF(ISNUMBER(H32),H32,G32) -> 18 | J32: =IF(D32="Manager",INPUTS!$C$35,IF(D32="Coordinator",INPUTS!$C$36,INPUTS!$C$29*INPUTS!$C$35+INPUTS!$C$30*INPUTS!$C$36)) -> 65 | K32: =IF(D32="Manager",INPUTS!$C$33,IF(D32="Coordinator",INPUTS!$C$34,INPUTS!$C$29*INPUTS!$C$33+INPUTS!$C$30*INPUTS!$C$34)) -> 42 | L32: =IF(E32="Yes",I32*J32,0) -> 0 | M32: =IF(E32="Yes",I32*K32,0) -> 0
A33: 30 | B33: VIP & PRESS LOGISTICS: Press Logistics | C33: VIP & PRESS LOGISTICS | D33: Coordinator | E33: No | F33: 8 x scale index | G33: =ROUND(8*INPUTS!$C$24,0) -> 12 | I33: =IF(ISNUMBER(H33),H33,G33) -> 12 | J33: =IF(D33="Manager",INPUTS!$C$35,IF(D33="Coordinator",INPUTS!$C$36,INPUTS!$C$29*INPUTS!$C$35+INPUTS!$C$30*INPUTS!$C$36)) -> 65 | K33: =IF(D33="Manager",INPUTS!$C$33,IF(D33="Coordinator",INPUTS!$C$34,INPUTS!$C$29*INPUTS!$C$33+INPUTS!$C$30*INPUTS!$C$34)) -> 42 | L33: =IF(E33="Yes",I33*J33,0) -> 0 | M33: =IF(E33="Yes",I33*K33,0) -> 0
A34: 31 | B34: SPONSORSHIPS: Sponsorship Opportunities | C34: SPONSORSHIPS | D34: Coordinator | E34: Yes | F34: 8 x scale index | G34: =ROUND(8*INPUTS!$C$24,0) -> 12 | I34: =IF(ISNUMBER(H34),H34,G34) -> 12 | J34: =IF(D34="Manager",INPUTS!$C$35,IF(D34="Coordinator",INPUTS!$C$36,INPUTS!$C$29*INPUTS!$C$35+INPUTS!$C$30*INPUTS!$C$36)) -> 65 | K34: =IF(D34="Manager",INPUTS!$C$33,IF(D34="Coordinator",INPUTS!$C$34,INPUTS!$C$29*INPUTS!$C$33+INPUTS!$C$30*INPUTS!$C$34)) -> 42 | L34: =IF(E34="Yes",I34*J34,0) -> 780 | M34: =IF(E34="Yes",I34*K34,0) -> 504
A35: 32 | B35: SPONSORSHIPS: Sponsor Management | C35: SPONSORSHIPS | D35: Coordinator | E35: Yes | F35: 1 hr per sponsor | G35: =ROUND(1*INPUTS!$C$12,0) -> 20 | I35: =IF(ISNUMBER(H35),H35,G35) -> 20 | J35: =IF(D35="Manager",INPUTS!$C$35,IF(D35="Coordinator",INPUTS!$C$36,INPUTS!$C$29*INPUTS!$C$35+INPUTS!$C$30*INPUTS!$C$36)) -> 65 | K35: =IF(D35="Manager",INPUTS!$C$33,IF(D35="Coordinator",INPUTS!$C$34,INPUTS!$C$29*INPUTS!$C$33+INPUTS!$C$30*INPUTS!$C$34)) -> 42 | L35: =IF(E35="Yes",I35*J35,0) -> 1300 | M35: =IF(E35="Yes",I35*K35,0) -> 840
A36: 33 | B36: SPEAKER MANAGEMENT: Speaker Prep | C36: SPEAKER MANAGEMENT | D36: Coordinator | E36: No | F36: 0.7 hrs per speaker | G36: =ROUND(0.7*INPUTS!$C$13,0) -> 11 | I36: =IF(ISNUMBER(H36),H36,G36) -> 11 | J36: =IF(D36="Manager",INPUTS!$C$35,IF(D36="Coordinator",INPUTS!$C$36,INPUTS!$C$29*INPUTS!$C$35+INPUTS!$C$30*INPUTS!$C$36)) -> 65 | K36: =IF(D36="Manager",INPUTS!$C$33,IF(D36="Coordinator",INPUTS!$C$34,INPUTS!$C$29*INPUTS!$C$33+INPUTS!$C$30*INPUTS!$C$34)) -> 42 | L36: =IF(E36="Yes",I36*J36,0) -> 0 | M36: =IF(E36="Yes",I36*K36,0) -> 0
A37: 34 | B37: SPEAKER MANAGEMENT: Speaker Management Onsite | C37: SPEAKER MANAGEMENT | D37: Coordinator | E37: No | F37: 0.3 hrs per speaker | G37: =ROUND(0.3*INPUTS!$C$13,0) -> 5 | I37: =IF(ISNUMBER(H37),H37,G37) -> 5 | J37: =IF(D37="Manager",INPUTS!$C$35,IF(D37="Coordinator",INPUTS!$C$36,INPUTS!$C$29*INPUTS!$C$35+INPUTS!$C$30*INPUTS!$C$36)) -> 65 | K37: =IF(D37="Manager",INPUTS!$C$33,IF(D37="Coordinator",INPUTS!$C$34,INPUTS!$C$29*INPUTS!$C$33+INPUTS!$C$30*INPUTS!$C$34)) -> 42 | L37: =IF(E37="Yes",I37*J37,0) -> 0 | M37: =IF(E37="Yes",I37*K37,0) -> 0
A38: 35 | B38: PROGRAMMING: Audio Visual | C38: PROGRAMMING | D38: Manager | E38: Yes | F38: 18 x scale index | G38: =ROUND(18*INPUTS!$C$24,0) -> 28 | I38: =IF(ISNUMBER(H38),H38,G38) -> 28 | J38: =IF(D38="Manager",INPUTS!$C$35,IF(D38="Coordinator",INPUTS!$C$36,INPUTS!$C$29*INPUTS!$C$35+INPUTS!$C$30*INPUTS!$C$36)) -> 90 | K38: =IF(D38="Manager",INPUTS!$C$33,IF(D38="Coordinator",INPUTS!$C$34,INPUTS!$C$29*INPUTS!$C$33+INPUTS!$C$30*INPUTS!$C$34)) -> 60 | L38: =IF(E38="Yes",I38*J38,0) -> 2520 | M38: =IF(E38="Yes",I38*K38,0) -> 1680
A39: 36 | B39: PROGRAMMING: Stage Production | C39: PROGRAMMING | D39: Manager | E39: Yes | F39: 15 x scale index | G39: =ROUND(15*INPUTS!$C$24,0) -> 23 | I39: =IF(ISNUMBER(H39),H39,G39) -> 23 | J39: =IF(D39="Manager",INPUTS!$C$35,IF(D39="Coordinator",INPUTS!$C$36,INPUTS!$C$29*INPUTS!$C$35+INPUTS!$C$30*INPUTS!$C$36)) -> 90 | K39: =IF(D39="Manager",INPUTS!$C$33,IF(D39="Coordinator",INPUTS!$C$34,INPUTS!$C$29*INPUTS!$C$33+INPUTS!$C$30*INPUTS!$C$34)) -> 60 | L39: =IF(E39="Yes",I39*J39,0) -> 2070 | M39: =IF(E39="Yes",I39*K39,0) -> 1380
A40: 37 | B40: PROGRAMMING: Entertainment & Talent | C40: PROGRAMMING | D40: Manager | E40: Yes | F40: 8 x scale index | G40: =ROUND(8*INPUTS!$C$24,0) -> 12 | I40: =IF(ISNUMBER(H40),H40,G40) -> 12 | J40: =IF(D40="Manager",INPUTS!$C$35,IF(D40="Coordinator",INPUTS!$C$36,INPUTS!$C$29*INPUTS!$C$35+INPUTS!$C$30*INPUTS!$C$36)) -> 90 | K40: =IF(D40="Manager",INPUTS!$C$33,IF(D40="Coordinator",INPUTS!$C$34,INPUTS!$C$29*INPUTS!$C$33+INPUTS!$C$30*INPUTS!$C$34)) -> 60 | L40: =IF(E40="Yes",I40*J40,0) -> 1080 | M40: =IF(E40="Yes",I40*K40,0) -> 720
A41: 38 | B41: PROGRAMMING: Recording & Broadcast — Pre-Event Coordination | C41: PROGRAMMING | D41: Manager | E41: No | F41: 8 x scale index | G41: =ROUND(8*INPUTS!$C$24,0) -> 12 | I41: =IF(ISNUMBER(H41),H41,G41) -> 12 | J41: =IF(D41="Manager",INPUTS!$C$35,IF(D41="Coordinator",INPUTS!$C$36,INPUTS!$C$29*INPUTS!$C$35+INPUTS!$C$30*INPUTS!$C$36)) -> 90 | K41: =IF(D41="Manager",INPUTS!$C$33,IF(D41="Coordinator",INPUTS!$C$34,INPUTS!$C$29*INPUTS!$C$33+INPUTS!$C$30*INPUTS!$C$34)) -> 60 | L41: =IF(E41="Yes",I41*J41,0) -> 0 | M41: =IF(E41="Yes",I41*K41,0) -> 0
A42: 39 | B42: PROGRAMMING: Recording & Broadcast — Onsite Support | C42: PROGRAMMING | D42: Manager | E42: No | F42: 10 x scale index | G42: =ROUND(10*INPUTS!$C$24,0) -> 15 | I42: =IF(ISNUMBER(H42),H42,G42) -> 15 | J42: =IF(D42="Manager",INPUTS!$C$35,IF(D42="Coordinator",INPUTS!$C$36,INPUTS!$C$29*INPUTS!$C$35+INPUTS!$C$30*INPUTS!$C$36)) -> 90 | K42: =IF(D42="Manager",INPUTS!$C$33,IF(D42="Coordinator",INPUTS!$C$34,INPUTS!$C$29*INPUTS!$C$33+INPUTS!$C$30*INPUTS!$C$34)) -> 60 | L42: =IF(E42="Yes",I42*J42,0) -> 0 | M42: =IF(E42="Yes",I42*K42,0) -> 0
A43: 40 | B43: RECEPTION PLANNING: Concept & Strategy | C43: RECEPTION PLANNING | D43: Coordinator | E43: No | F43: 3 x scale index | G43: =ROUND(3*INPUTS!$C$24,0) -> 5 | I43: =IF(ISNUMBER(H43),H43,G43) -> 5 | J43: =IF(D43="Manager",INPUTS!$C$35,IF(D43="Coordinator",INPUTS!$C$36,INPUTS!$C$29*INPUTS!$C$35+INPUTS!$C$30*INPUTS!$C$36)) -> 65 | K43: =IF(D43="Manager",INPUTS!$C$33,IF(D43="Coordinator",INPUTS!$C$34,INPUTS!$C$29*INPUTS!$C$33+INPUTS!$C$30*INPUTS!$C$34)) -> 42 | L43: =IF(E43="Yes",I43*J43,0) -> 0 | M43: =IF(E43="Yes",I43*K43,0) -> 0
A44: 41 | B44: RECEPTION PLANNING: Venue & Layout | C44: RECEPTION PLANNING | D44: Coordinator | E44: No | F44: 4 x scale index | G44: =ROUND(4*INPUTS!$C$24,0) -> 6 | I44: =IF(ISNUMBER(H44),H44,G44) -> 6 | J44: =IF(D44="Manager",INPUTS!$C$35,IF(D44="Coordinator",INPUTS!$C$36,INPUTS!$C$29*INPUTS!$C$35+INPUTS!$C$30*INPUTS!$C$36)) -> 65 | K44: =IF(D44="Manager",INPUTS!$C$33,IF(D44="Coordinator",INPUTS!$C$34,INPUTS!$C$29*INPUTS!$C$33+INPUTS!$C$30*INPUTS!$C$34)) -> 42 | L44: =IF(E44="Yes",I44*J44,0) -> 0 | M44: =IF(E44="Yes",I44*K44,0) -> 0
A45: 42 | B45: RECEPTION PLANNING: Food & Beverage | C45: RECEPTION PLANNING | D45: Coordinator | E45: No | F45: 4 x scale index | G45: =ROUND(4*INPUTS!$C$24,0) -> 6 | I45: =IF(ISNUMBER(H45),H45,G45) -> 6 | J45: =IF(D45="Manager",INPUTS!$C$35,IF(D45="Coordinator",INPUTS!$C$36,INPUTS!$C$29*INPUTS!$C$35+INPUTS!$C$30*INPUTS!$C$36)) -> 65 | K45: =IF(D45="Manager",INPUTS!$C$33,IF(D45="Coordinator",INPUTS!$C$34,INPUTS!$C$29*INPUTS!$C$33+INPUTS!$C$30*INPUTS!$C$34)) -> 42 | L45: =IF(E45="Yes",I45*J45,0) -> 0 | M45: =IF(E45="Yes",I45*K45,0) -> 0
A46: 43 | B46: RECEPTION PLANNING: Entertainment & Atmosphere | C46: RECEPTION PLANNING | D46: Coordinator | E46: No | F46: 3 x scale index | G46: =ROUND(3*INPUTS!$C$24,0) -> 5 | I46: =IF(ISNUMBER(H46),H46,G46) -> 5 | J46: =IF(D46="Manager",INPUTS!$C$35,IF(D46="Coordinator",INPUTS!$C$36,INPUTS!$C$29*INPUTS!$C$35+INPUTS!$C$30*INPUTS!$C$36)) -> 65 | K46: =IF(D46="Manager",INPUTS!$C$33,IF(D46="Coordinator",INPUTS!$C$34,INPUTS!$C$29*INPUTS!$C$33+INPUTS!$C$30*INPUTS!$C$34)) -> 42 | L46: =IF(E46="Yes",I46*J46,0) -> 0 | M46: =IF(E46="Yes",I46*K46,0) -> 0
A47: 44 | B47: RECEPTION PLANNING: Guest Experience | C47: RECEPTION PLANNING | D47: Coordinator | E47: No | F47: 3 x scale index | G47: =ROUND(3*INPUTS!$C$24,0) -> 5 | I47: =IF(ISNUMBER(H47),H47,G47) -> 5 | J47: =IF(D47="Manager",INPUTS!$C$35,IF(D47="Coordinator",INPUTS!$C$36,INPUTS!$C$29*INPUTS!$C$35+INPUTS!$C$30*INPUTS!$C$36)) -> 65 | K47: =IF(D47="Manager",INPUTS!$C$33,IF(D47="Coordinator",INPUTS!$C$34,INPUTS!$C$29*INPUTS!$C$33+INPUTS!$C$30*INPUTS!$C$34)) -> 42 | L47: =IF(E47="Yes",I47*J47,0) -> 0 | M47: =IF(E47="Yes",I47*K47,0) -> 0
A48: 45 | B48: RECEPTION PLANNING: Staffing & Logistics | C48: RECEPTION PLANNING | D48: Coordinator | E48: No | F48: 3 x scale index | G48: =ROUND(3*INPUTS!$C$24,0) -> 5 | I48: =IF(ISNUMBER(H48),H48,G48) -> 5 | J48: =IF(D48="Manager",INPUTS!$C$35,IF(D48="Coordinator",INPUTS!$C$36,INPUTS!$C$29*INPUTS!$C$35+INPUTS!$C$30*INPUTS!$C$36)) -> 65 | K48: =IF(D48="Manager",INPUTS!$C$33,IF(D48="Coordinator",INPUTS!$C$34,INPUTS!$C$29*INPUTS!$C$33+INPUTS!$C$30*INPUTS!$C$34)) -> 42 | L48: =IF(E48="Yes",I48*J48,0) -> 0 | M48: =IF(E48="Yes",I48*K48,0) -> 0
A49: 46 | B49: RECEPTION PLANNING: Capture & Follow-Up | C49: RECEPTION PLANNING | D49: Coordinator | E49: No | F49: 2 x scale index | G49: =ROUND(2*INPUTS!$C$24,0) -> 3 | I49: =IF(ISNUMBER(H49),H49,G49) -> 3 | J49: =IF(D49="Manager",INPUTS!$C$35,IF(D49="Coordinator",INPUTS!$C$36,INPUTS!$C$29*INPUTS!$C$35+INPUTS!$C$30*INPUTS!$C$36)) -> 65 | K49: =IF(D49="Manager",INPUTS!$C$33,IF(D49="Coordinator",INPUTS!$C$34,INPUTS!$C$29*INPUTS!$C$33+INPUTS!$C$30*INPUTS!$C$34)) -> 42 | L49: =IF(E49="Yes",I49*J49,0) -> 0 | M49: =IF(E49="Yes",I49*K49,0) -> 0
A50: 47 | B50: FINANCIAL MANAGEMENT: Budgets, Reporting & Billing | C50: FINANCIAL MANAGEMENT | D50: Manager | E50: Yes | F50: 12 x scale index | G50: =ROUND(12*INPUTS!$C$24,0) -> 18 | I50: =IF(ISNUMBER(H50),H50,G50) -> 18 | J50: =IF(D50="Manager",INPUTS!$C$35,IF(D50="Coordinator",INPUTS!$C$36,INPUTS!$C$29*INPUTS!$C$35+INPUTS!$C$30*INPUTS!$C$36)) -> 90 | K50: =IF(D50="Manager",INPUTS!$C$33,IF(D50="Coordinator",INPUTS!$C$34,INPUTS!$C$29*INPUTS!$C$33+INPUTS!$C$30*INPUTS!$C$34)) -> 60 | L50: =IF(E50="Yes",I50*J50,0) -> 1620 | M50: =IF(E50="Yes",I50*K50,0) -> 1080
A51: 48 | B51: EVENT MARKETING: Strategy & Timeline | C51: EVENT MARKETING | D51: Manager | E51: No | F51: 8 x scale index | G51: =ROUND(8*INPUTS!$C$24,0) -> 12 | I51: =IF(ISNUMBER(H51),H51,G51) -> 12 | J51: =IF(D51="Manager",INPUTS!$C$35,IF(D51="Coordinator",INPUTS!$C$36,INPUTS!$C$29*INPUTS!$C$35+INPUTS!$C$30*INPUTS!$C$36)) -> 90 | K51: =IF(D51="Manager",INPUTS!$C$33,IF(D51="Coordinator",INPUTS!$C$34,INPUTS!$C$29*INPUTS!$C$33+INPUTS!$C$30*INPUTS!$C$34)) -> 60 | L51: =IF(E51="Yes",I51*J51,0) -> 0 | M51: =IF(E51="Yes",I51*K51,0) -> 0
A52: 49 | B52: EVENT MARKETING: Social Media & Email Campaigns | C52: EVENT MARKETING | D52: Manager | E52: No | F52: 9 x scale index | G52: =ROUND(9*INPUTS!$C$24,0) -> 14 | I52: =IF(ISNUMBER(H52),H52,G52) -> 14 | J52: =IF(D52="Manager",INPUTS!$C$35,IF(D52="Coordinator",INPUTS!$C$36,INPUTS!$C$29*INPUTS!$C$35+INPUTS!$C$30*INPUTS!$C$36)) -> 90 | K52: =IF(D52="Manager",INPUTS!$C$33,IF(D52="Coordinator",INPUTS!$C$34,INPUTS!$C$29*INPUTS!$C$33+INPUTS!$C$30*INPUTS!$C$34)) -> 60 | L52: =IF(E52="Yes",I52*J52,0) -> 0 | M52: =IF(E52="Yes",I52*K52,0) -> 0
A53: 50 | B53: EVENT MARKETING: Messaging | C53: EVENT MARKETING | D53: Manager | E53: No | F53: 5 x scale index | G53: =ROUND(5*INPUTS!$C$24,0) -> 8 | I53: =IF(ISNUMBER(H53),H53,G53) -> 8 | J53: =IF(D53="Manager",INPUTS!$C$35,IF(D53="Coordinator",INPUTS!$C$36,INPUTS!$C$29*INPUTS!$C$35+INPUTS!$C$30*INPUTS!$C$36)) -> 90 | K53: =IF(D53="Manager",INPUTS!$C$33,IF(D53="Coordinator",INPUTS!$C$34,INPUTS!$C$29*INPUTS!$C$33+INPUTS!$C$30*INPUTS!$C$34)) -> 60 | L53: =IF(E53="Yes",I53*J53,0) -> 0 | M53: =IF(E53="Yes",I53*K53,0) -> 0
A54: 51 | B54: EVENT MARKETING: Marketing Assistance | C54: EVENT MARKETING | D54: Manager | E54: No | F54: 5 x scale index | G54: =ROUND(5*INPUTS!$C$24,0) -> 8 | I54: =IF(ISNUMBER(H54),H54,G54) -> 8 | J54: =IF(D54="Manager",INPUTS!$C$35,IF(D54="Coordinator",INPUTS!$C$36,INPUTS!$C$29*INPUTS!$C$35+INPUTS!$C$30*INPUTS!$C$36)) -> 90 | K54: =IF(D54="Manager",INPUTS!$C$33,IF(D54="Coordinator",INPUTS!$C$34,INPUTS!$C$29*INPUTS!$C$33+INPUTS!$C$30*INPUTS!$C$34)) -> 60 | L54: =IF(E54="Yes",I54*J54,0) -> 0 | M54: =IF(E54="Yes",I54*K54,0) -> 0
A55: 52 | B55: EXHIBIT MANAGEMENT: Exhibitor Planning & Onsite Execution | C55: EXHIBIT MANAGEMENT | D55: Manager | E55: Yes | F55: 1 hr per exhibitor | G55: =ROUND(1*INPUTS!$C$11,0) -> 60 | I55: =IF(ISNUMBER(H55),H55,G55) -> 60 | J55: =IF(D55="Manager",INPUTS!$C$35,IF(D55="Coordinator",INPUTS!$C$36,INPUTS!$C$29*INPUTS!$C$35+INPUTS!$C$30*INPUTS!$C$36)) -> 90 | K55: =IF(D55="Manager",INPUTS!$C$33,IF(D55="Coordinator",INPUTS!$C$34,INPUTS!$C$29*INPUTS!$C$33+INPUTS!$C$30*INPUTS!$C$34)) -> 60 | L55: =IF(E55="Yes",I55*J55,0) -> 5400 | M55: =IF(E55="Yes",I55*K55,0) -> 3600
A56: 53 | B56: POST-EVENT: Debrief, Reporting & Recommendations | C56: POST-EVENT | D56: Manager | E56: Yes | F56: 10 x scale index | G56: =ROUND(10*INPUTS!$C$24,0) -> 15 | I56: =IF(ISNUMBER(H56),H56,G56) -> 15 | J56: =IF(D56="Manager",INPUTS!$C$35,IF(D56="Coordinator",INPUTS!$C$36,INPUTS!$C$29*INPUTS!$C$35+INPUTS!$C$30*INPUTS!$C$36)) -> 90 | K56: =IF(D56="Manager",INPUTS!$C$33,IF(D56="Coordinator",INPUTS!$C$34,INPUTS!$C$29*INPUTS!$C$33+INPUTS!$C$30*INPUTS!$C$34)) -> 60 | L56: =IF(E56="Yes",I56*J56,0) -> 1350 | M56: =IF(E56="Yes",I56*K56,0) -> 900
A57: 54 | B57: TOURNAMENTS: Venue Booking & Coordination | C57: TOURNAMENTS | D57: Coordinator | E57: No | F57: 7 x scale index | G57: =ROUND(7*INPUTS!$C$24,0) -> 11 | I57: =IF(ISNUMBER(H57),H57,G57) -> 11 | J57: =IF(D57="Manager",INPUTS!$C$35,IF(D57="Coordinator",INPUTS!$C$36,INPUTS!$C$29*INPUTS!$C$35+INPUTS!$C$30*INPUTS!$C$36)) -> 65 | K57: =IF(D57="Manager",INPUTS!$C$33,IF(D57="Coordinator",INPUTS!$C$34,INPUTS!$C$29*INPUTS!$C$33+INPUTS!$C$30*INPUTS!$C$34)) -> 42 | L57: =IF(E57="Yes",I57*J57,0) -> 0 | M57: =IF(E57="Yes",I57*K57,0) -> 0
A58: 55 | B58: TOURNAMENTS: Registration & Communications | C58: TOURNAMENTS | D58: Coordinator | E58: No | F58: 8 x scale index | G58: =ROUND(8*INPUTS!$C$24,0) -> 12 | I58: =IF(ISNUMBER(H58),H58,G58) -> 12 | J58: =IF(D58="Manager",INPUTS!$C$35,IF(D58="Coordinator",INPUTS!$C$36,INPUTS!$C$29*INPUTS!$C$35+INPUTS!$C$30*INPUTS!$C$36)) -> 65 | K58: =IF(D58="Manager",INPUTS!$C$33,IF(D58="Coordinator",INPUTS!$C$34,INPUTS!$C$29*INPUTS!$C$33+INPUTS!$C$30*INPUTS!$C$34)) -> 42 | L58: =IF(E58="Yes",I58*J58,0) -> 0 | M58: =IF(E58="Yes",I58*K58,0) -> 0
A59: 56 | B59: TOURNAMENTS: Check-In & Onsite Management | C59: TOURNAMENTS | D59: Coordinator | E59: No | F59: 7 x scale index | G59: =ROUND(7*INPUTS!$C$24,0) -> 11 | I59: =IF(ISNUMBER(H59),H59,G59) -> 11 | J59: =IF(D59="Manager",INPUTS!$C$35,IF(D59="Coordinator",INPUTS!$C$36,INPUTS!$C$29*INPUTS!$C$35+INPUTS!$C$30*INPUTS!$C$36)) -> 65 | K59: =IF(D59="Manager",INPUTS!$C$33,IF(D59="Coordinator",INPUTS!$C$34,INPUTS!$C$29*INPUTS!$C$33+INPUTS!$C$30*INPUTS!$C$34)) -> 42 | L59: =IF(E59="Yes",I59*J59,0) -> 0 | M59: =IF(E59="Yes",I59*K59,0) -> 0
B60: TOTAL — INCLUDED SCOPE | I60: =SUMIF($E$4:$E$59,"Yes",$I$4:$I$59) -> 568 | L60: =SUM(L4:L59) -> 48830 | M60: =SUM(M4:M59) -> 32244

Sheet HOW TO USE
B1: HOW TO BUILD A NEW CONFERENCE P&L
B3: STEP 1 — INPUTS
B4: • Event size: attendees, exhibitors, sponsors, speakers, vendors to source, site visits.
B5: • Schedule: event days, set-up days, travel days, months of pre-planning.
B6: • Staffing: how many managers and coordinators onsite, and how many in pre-planning.
B7: • Rates are pre-set — manager $60/hr cost, coordinator $42/hr cost. Change only if the rate card changes.
B9: STEP 2 — SCOPE
B10: • Every line matches the Master Proposal Template, sub-item by sub-item. Set INCLUDE? to Yes or No on each.
B11: • Hours calculate automatically. Disagree with a line? Type your number into OVERRIDE HOURS — nothing else changes.
B13: STEP 3 — P&L
B14: • Nothing to type. Scope rolls up to the top-level proposal headings, so the P&L reads the same way the proposal does.
B15: • Watch HRS / PERSON / WEEK — above roughly 10 the headcount is too thin for the scope.
... B28: • MULTI-YEAR DISCOUNT = the 5% off additional years. Off by default — switch it on at the bottom of INPUTS section 7.
